{"code": "ELCT", "description": "Electrical", "entries": 31, "data": [{"id": 140425, "term": "202420", "termDesc": "Fall 2024", "courseReferenceNumber": "21312", "partOfTerm": "1", "courseNumber": "205", "subject": "ELCT", "subjectDescription": "Electrical", "sequenceNumber": "A", "campusDescription": "Main Campus", "scheduleTypeDescription": "Lecture", "courseTitle": "Electrical Principles", "creditHours": 3, "maximumEnrollment": 32, "enrollment": 0, "seatsAvailable": 32, "waitCapacity": 0, "waitCount": 0, "waitAvailable": 0, "crossList": null, "crossListCapacity": null, "crossListCount": null, "crossListAvailable": null, "creditHourHigh": 3, "creditHourLow": 0, "creditHourIndicator": "OR", "openSection": true, "linkIdentifier": "A1", "isSectionLinked": true, "subjectCourse": "ELCT205", "faculty": [], "meetingsFaculty": [{"category": "01", "class": "net.hedtech.banner.student.schedule.SectionSessionDecorator", "courseReferenceNumber": "21312", "faculty": [], "meetingTime": {"beginTime": "0800", "building": "KA", "buildingDescription": "Johnson-Cobbe Energy Centre", "campus": "MC", "campusDescription": "Main Campus", "category": "01", "class": "net.hedtech.banner.general.overall.MeetingTimeDecorator", "courseReferenceNumber": "21312", "creditHourSession": 0.0, "endDate": "12/16/2024", "endTime": "0950", "friday": false, "hoursWeek": 2.0, "meetingScheduleType": "L", "meetingType": "CLAS", "meetingTypeDescription": "Class", "monday": true, "room": "KA230", "saturday": false, "startDate": "09/03/2024", "sunday": false, "term": "202420", "thursday": false, "tuesday": false, "wednesday": false}, "term": "202420"}, {"category": "01", "class": "net.hedtech.banner.student.schedule.SectionSessionDecorator", "courseReferenceNumber": "21312", "faculty": [], "meetingTime": {"beginTime": "1000", "building": "KA", "buildingDescription": "Johnson-Cobbe Energy Centre", "campus": "MC", "campusDescription": "Main Campus", "category": "01", "class": "net.hedtech.banner.general.overall.MeetingTimeDecorator", "courseReferenceNumber": "21312", "creditHourSession": 3.0, "endDate": "12/16/2024", "endTime": "1150", "friday": false, "hoursWeek": 2.0, "meetingScheduleType": "L", "meetingType": "CLAS", "meetingTypeDescription": "Class", "monday": false, "room": "KA230", "saturday": false, "startDate": "09/03/2024", "sunday": false, "term": "202420", "thursday": true, "tuesday": false, "wednesday": false}, "term": "202420"}, {"category": "01", "class": "net.hedtech.banner.student.schedule.SectionSessionDecorator", "courseReferenceNumber": "21312", "faculty": [], "meetingTime": {"beginTime": "1200", "building": "KA", "buildingDescription": "Johnson-Cobbe Energy Centre", "campus": "MC", "campusDescription": "Main Campus", "category": "01", "class": "net.hedtech.banner.general.overall.MeetingTimeDecorator", "courseReferenceNumber": "21312", "creditHourSession": 0.0, "endDate": "12/16/2024", "endTime": "1350", "friday": false, "hoursWeek": 2.0, "meetingScheduleType": "L", "meetingType": "CLAS", "meetingTypeDescription": "Class", "monday": false, "room": "KA218", "saturday": false, "startDate": "09/03/2024", "sunday": false, "term": "202420", "thursday": false, "tuesday": true, "wednesday": false}, "term": "202420"}], "reservedSeatSummary": null, "sectionAttributes": [], "instructionalMethod": "IP", "instructionalMethodDescription": "In Person"}, {"id": 140430, "term": "202420", "termDesc": "Fall 2024", "courseReferenceNumber": "21313", "partOfTerm": "1", "courseNumber": "205", "subject": "ELCT", "subjectDescription": "Electrical", "sequenceNumber": "AA", "campusDescription": "Main Campus", "scheduleTypeDescription": "Laboratory", "courseTitle": "Electrical Principles", "creditHours": 0, "maximumEnrollment": 16, "enrollment": 0, "seatsAvailable": 16, "waitCapacity": 0, "waitCount": 0, "waitAvailable": 0, "crossList": null, "crossListCapacity": null, "crossListCount": null, "crossListAvailable": null, "creditHourHigh": 3, "creditHourLow": 0, "creditHourIndicator": "OR", "openSection": true, "linkIdentifier": "K1", "isSectionLinked": true, "subjectCourse": "ELCT205", "faculty": [], "meetingsFaculty": [{"category": "01", "class": "net.hedtech.banner.student.schedule.SectionSessionDecorator", "courseReferenceNumber": "21313", "faculty": [], "meetingTime": {"beginTime": "1000", "building": "KA", "buildingDescription": "Johnson-Cobbe Energy Centre", "campus": "MC", "campusDescription": "Main Campus", "category": "01", "class": "net.hedtech.banner.general.overall.MeetingTimeDecorator", "courseReferenceNumber": "21313", "creditHourSession": 0.0, "endDate": "12/16/2024", "endTime": "1150", "friday": false, "hoursWeek": 2.0, "meetingScheduleType": "B", "meetingType": "CLAS", "meetingTypeDescription": "Class", "monday": false, "room": "KA012", "saturday": false, "startDate": "09/03/2024", "sunday": false, "term": "202420", "thursday": false, "tuesday": false, "wednesday": true}, "term": "202420"}], "reservedSeatSummary": null, "sectionAttributes": [], "instructionalMethod": "IP", "instructionalMethodDescription": "In Person"}, {"id": 142235, "term": "202420", "termDesc": "Fall 2024", "courseReferenceNumber": "21314", "partOfTerm": "1", "courseNumber": "205", "subject": "ELCT", "subjectDescription": "Electrical", "sequenceNumber": "AAA", "campusDescription": "Main Campus", "scheduleTypeDescription": "Laboratory", "courseTitle": "Electrical Principles", "creditHours": 0, "maximumEnrollment": 16, "enrollment": 0, "seatsAvailable": 16, "waitCapacity": 0, "waitCount": 0, "waitAvailable": 0, "crossList": null, "crossListCapacity": null, "crossListCount": null, "crossListAvailable": null, "creditHourHigh": 3, "creditHourLow": 0, "creditHourIndicator": "OR", "openSection": true, "linkIdentifier": "K1", "isSectionLinked": true, "subjectCourse": "ELCT205", "faculty": [], "meetingsFaculty": [{"category": "01", "class": "net.hedtech.banner.student.schedule.SectionSessionDecorator", "courseReferenceNumber": "21314", "faculty": [], "meetingTime": {"beginTime": "1500", "building": "KA", "buildingDescription": "Johnson-Cobbe Energy Centre", "campus": "MC", "campusDescription": "Main Campus", "category": "01", "class": "net.hedtech.banner.general.overall.MeetingTimeDecorator", "courseReferenceNumber": "21314", "creditHourSession": 0.0, "endDate": "12/16/2024", "endTime": "1650", "friday": true, "hoursWeek": 2.0, "meetingScheduleType": "B", "meetingType": "CLAS", "meetingTypeDescription": "Class", "monday": false, "room": "KA012", "saturday": false, "startDate": "09/03/2024", "sunday": false, "term": "202420", "thursday": false, "tuesday": false, "wednesday": false}, "term": "202420"}], "reservedSeatSummary": null, "sectionAttributes": [], "instructionalMethod": "IP", "instructionalMethodDescription": "In Person"}, {"id": 140431, "term": "202420", "termDesc": "Fall 2024", "courseReferenceNumber": "21315", "partOfTerm": "1", "courseNumber": "205", "subject": "ELCT", "subjectDescription": "Electrical", "sequenceNumber": "B", "campusDescription": "Main Campus", "scheduleTypeDescription": "Lecture", "courseTitle": "Electrical Principles", "creditHours": 3, "maximumEnrollment": 32, "enrollment": 0, "seatsAvailable": 32, "waitCapacity": 0, "waitCount": 0, "waitAvailable": 0, "crossList": null, "crossListCapacity": null, "crossListCount": null, "crossListAvailable": null, "creditHourHigh": 3, "creditHourLow": 0, "creditHourIndicator": "OR", "openSection": true, "linkIdentifier": "A2", "isSectionLinked": true, "subjectCourse": "ELCT205", "faculty": [], "meetingsFaculty": [{"category": "01", "class": "net.hedtech.banner.student.schedule.SectionSessionDecorator", "courseReferenceNumber": "21315", "faculty": [], "meetingTime": {"beginTime": "1000", "building": "KA", "buildingDescription": "Johnson-Cobbe Energy Centre", "campus": "MC", "campusDescription": "Main Campus", "category": "01", "class": "net.hedtech.banner.general.overall.MeetingTimeDecorator", "courseReferenceNumber": "21315", "creditHourSession": 0.0, "endDate": "12/16/2024", "endTime": "1150", "friday": false, "hoursWeek": 2.0, "meetingScheduleType": "L", "meetingType": "CLAS", "meetingTypeDescription": "Class", "monday": true, "room": "KA204", "saturday": false, "startDate": "09/03/2024", "sunday": false, "term": "202420", "thursday": false, "tuesday": false, "wednesday": false}, "term": "202420"}, {"category": "01", "class": "net.hedtech.banner.student.schedule.SectionSessionDecorator", "courseReferenceNumber": "21315", "faculty": [], "meetingTime": {"beginTime": "1000", "building": "KA", "buildingDescription": "Johnson-Cobbe Energy Centre", "campus": "MC", "campusDescription": "Main Campus", "category": "01", "class": "net.hedtech.banner.general.overall.MeetingTimeDecorator", "courseReferenceNumber": "21315", "creditHourSession": 3.0, "endDate": "12/16/2024", "endTime": "1150", "friday": true, "hoursWeek": 2.0, "meetingScheduleType": "L", "meetingType": "CLAS", "meetingTypeDescription": "Class", "monday": false, "room": "KA230", "saturday": false, "startDate": "09/03/2024", "sunday": false, "term": "202420", "thursday": false, "tuesday": false, "wednesday": false}, "term": "202420"}, {"category": "01", "class": "net.hedtech.banner.student.schedule.SectionSessionDecorator", "courseReferenceNumber": "21315", "faculty": [], "meetingTime": {"beginTime": "1500", "building": "KA", "buildingDescription": "Johnson-Cobbe Energy Centre", "campus": "MC", "campusDescription": "Main Campus", "category": "01", "class": "net.hedtech.banner.general.overall.MeetingTimeDecorator", "courseReferenceNumber": "21315", "creditHourSession": 0.0, "endDate": "12/16/2024", "endTime": "1650", "friday": false, "hoursWeek": 2.0, "meetingScheduleType": "L", "meetingType": "CLAS", "meetingTypeDescription": "Class", "monday": false, "room": "KA218", "saturday": false, "startDate": "09/03/2024", "sunday": false, "term": "202420", "thursday": false, "tuesday": true, "wednesday": false}, "term": "202420"}], "reservedSeatSummary": null, "sectionAttributes": [], "instructionalMethod": "IP", "instructionalMethodDescription": "In Person"}, {"id": 140156, "term": "202420", "termDesc": "Fall 2024", "courseReferenceNumber": "21316", "partOfTerm": "1", "courseNumber": "205", "subject": "ELCT", "subjectDescription": "Electrical", "sequenceNumber": "B1", "campusDescription": "Main Campus", "scheduleTypeDescription": "Lecture", "courseTitle": "Electrical Principles", "creditHours": 3, "maximumEnrollment": 16, "enrollment": 0, "seatsAvailable": 16, "waitCapacity": 0, "waitCount": 0, "waitAvailable": 0, "crossList": null, "crossListCapacity": null, "crossListCount": null, "crossListAvailable": null, "creditHourHigh": 3, "creditHourLow": 0, "creditHourIndicator": "OR", "openSection": true, "linkIdentifier": null, "isSectionLinked": false, "subjectCourse": "ELCT205", "faculty": [], "meetingsFaculty": [{"category": "01", "class": "net.hedtech.banner.student.schedule.SectionSessionDecorator", "courseReferenceNumber": "21316", "faculty": [], "meetingTime": {"beginTime": "1000", "building": "KA", "buildingDescription": "Johnson-Cobbe Energy Centre", "campus": "MC", "campusDescription": "Main Campus", "category": "01", "class": "net.hedtech.banner.general.overall.MeetingTimeDecorator", "courseReferenceNumber": "21316", "creditHourSession": 0.0, "endDate": "10/05/2024", "endTime": "1350", "friday": false, "hoursWeek": 4.0, "meetingScheduleType": "L", "meetingType": "CLAS", "meetingTypeDescription": "Class", "monday": false, "room": "KA208", "saturday": true, "startDate": "09/03/2024", "sunday": false, "term": "202420", "thursday": false, "tuesday": false, "wednesday": false}, "term": "202420"}, {"category": "01", "class": "net.hedtech.banner.student.schedule.SectionSessionDecorator", "courseReferenceNumber": "21316", "faculty": [], "meetingTime": {"beginTime": "1000", "building": "KA", "buildingDescription": "Johnson-Cobbe Energy Centre", "campus": "MC", "campusDescription": "Main Campus", "category": "01", "class": "net.hedtech.banner.general.overall.MeetingTimeDecorator", "courseReferenceNumber": "21316", "creditHourSession": 0.0, "endDate": "11/16/2024", "endTime": "1350", "friday": false, "hoursWeek": 4.0, "meetingScheduleType": "L", "meetingType": "CLAS", "meetingTypeDescription": "Class", "monday": false, "room": "KA208", "saturday": true, "startDate": "10/19/2024", "sunday": false, "term": "202420", "thursday": false, "tuesday": false, "wednesday": false}, "term": "202420"}, {"category": "01", "class": "net.hedtech.banner.student.schedule.SectionSessionDecorator", "courseReferenceNumber": "21316", "faculty": [], "meetingTime": {"beginTime": "1000", "building": "KA", "buildingDescription": "Johnson-Cobbe Energy Centre", "campus": "MC", "campusDescription": "Main Campus", "category": "01", "class": "net.hedtech.banner.general.overall.MeetingTimeDecorator", "courseReferenceNumber": "21316", "creditHourSession": 0.0, "endDate": "12/13/2024", "endTime": "1350", "friday": false, "hoursWeek": 4.0, "meetingScheduleType": "L", "meetingType": "CLAS", "meetingTypeDescription": "Class", "monday": false, "room": "KA208", "saturday": true, "startDate": "11/30/2024", "sunday": false, "term": "202420", "thursday": false, "tuesday": false, "wednesday": false}, "term": "202420"}, {"category": "01", "class": "net.hedtech.banner.student.schedule.SectionSessionDecorator", "courseReferenceNumber": "21316", "faculty": [], "meetingTime": {"beginTime": "1800", "building": "T", "buildingDescription": "Thomas Riley Building", "campus": "MC", "campusDescription": "Main Campus", "category": "01", "class": "net.hedtech.banner.general.overall.MeetingTimeDecorator", "courseReferenceNumber": "21316", "creditHourSession": 3.0, "endDate": "12/13/2024", "endTime": "1950", "friday": false, "hoursWeek": 4.0, "meetingScheduleType": "L", "meetingType": "CLAS", "meetingTypeDescription": "Class", "monday": false, "room": "TT236", "saturday": false, "startDate": "09/03/2024", "sunday": false, "term": "202420", "thursday": true, "tuesday": true, "wednesday": false}, "term": "202420"}], "reservedSeatSummary": null, "sectionAttributes": [], "instructionalMethod": "IP", "instructionalMethodDescription": "In Person"}, {"id": 140432, "term": "202420", "termDesc": "Fall 2024", "courseReferenceNumber": "21317", "partOfTerm": "1", "courseNumber": "205", "subject": "ELCT", "subjectDescription": "Electrical", "sequenceNumber": "BB", "campusDescription": "Main Campus", "scheduleTypeDescription": "Laboratory", "courseTitle": "Electrical Principles", "creditHours": 0, "maximumEnrollment": 16, "enrollment": 0, "seatsAvailable": 16, "waitCapacity": 0, "waitCount": 0, "waitAvailable": 0, "crossList": null, "crossListCapacity": null, "crossListCount": null, "crossListAvailable": null, "creditHourHigh": 3, "creditHourLow": 0, "creditHourIndicator": "OR", "openSection": true, "linkIdentifier": "K2", "isSectionLinked": true, "subjectCourse": "ELCT205", "faculty": [], "meetingsFaculty": [{"category": "01", "class": "net.hedtech.banner.student.schedule.SectionSessionDecorator", "courseReferenceNumber": "21317", "faculty": [], "meetingTime": {"beginTime": "1300", "building": "KA", "buildingDescription": "Johnson-Cobbe Energy Centre", "campus": "MC", "campusDescription": "Main Campus", "category": "01", "class": "net.hedtech.banner.general.overall.MeetingTimeDecorator", "courseReferenceNumber": "21317", "creditHourSession": 0.0, "endDate": "12/16/2024", "endTime": "1450", "friday": false, "hoursWeek": 2.0, "meetingScheduleType": "B", "meetingType": "CLAS", "meetingTypeDescription": "Class", "monday": false, "room": "KA012", "saturday": false, "startDate": "09/03/2024", "sunday": false, "term": "202420", "thursday": false, "tuesday": false, "wednesday": true}, "term": "202420"}], "reservedSeatSummary": null, "sectionAttributes": [], "instructionalMethod": "IP", "instructionalMethodDescription": "In Person"}, {"id": 142236, "term": "202420", "termDesc": "Fall 2024", "courseReferenceNumber": "21318", "partOfTerm": "1", "courseNumber": "205", "subject": "ELCT", "subjectDescription": "Electrical", "sequenceNumber": "BBB", "campusDescription": "Main Campus", "scheduleTypeDescription": "Laboratory", "courseTitle": "Electrical Principles", "creditHours": 0, "maximumEnrollment": 16, "enrollment": 0, "seatsAvailable": 16, "waitCapacity": 0, "waitCount": 0, "waitAvailable": 0, "crossList": null, "crossListCapacity": null, "crossListCount": null, "crossListAvailable": null, "creditHourHigh": 3, "creditHourLow": 0, "creditHourIndicator": "OR", "openSection": true, "linkIdentifier": "K2", "isSectionLinked": true, "subjectCourse": "ELCT205", "faculty": [], "meetingsFaculty": [{"category": "01", "class": "net.hedtech.banner.student.schedule.SectionSessionDecorator", "courseReferenceNumber": "21318", "faculty": [], "meetingTime": {"beginTime": "1500", "building": "KA", "buildingDescription": "Johnson-Cobbe Energy Centre", "campus": "MC", "campusDescription": "Main Campus", "category": "01", "class": "net.hedtech.banner.general.overall.MeetingTimeDecorator", "courseReferenceNumber": "21318", "creditHourSession": 0.0, "endDate": "12/16/2024", "endTime": "1650", "friday": false, "hoursWeek": 2.0, "meetingScheduleType": "B", "meetingType": "CLAS", "meetingTypeDescription": "Class", "monday": true, "room": "KA012", "saturday": false, "startDate": "09/03/2024", "sunday": false, "term": "202420", "thursday": false, "tuesday": false, "wednesday": false}, "term": "202420"}], "reservedSeatSummary": null, "sectionAttributes": [], "instructionalMethod": "IP", "instructionalMethodDescription": "In Person"}, {"id": 141221, "term": "202420", "termDesc": "Fall 2024", "courseReferenceNumber": "21319", "partOfTerm": "1", "courseNumber": "254", "subject": "ELCT", "subjectDescription": "Electrical", "sequenceNumber": "A", "campusDescription": "Main Campus", "scheduleTypeDescription": "Lecture", "courseTitle": "Electrical and Controls I", "creditHours": 1.5, "maximumEnrollment": 32, "enrollment": 0, "seatsAvailable": 32, "waitCapacity": 0, "waitCount": 0, "waitAvailable": 0, "crossList": null, "crossListCapacity": null, "crossListCount": null, "crossListAvailable": null, "creditHourHigh": 1.5, "creditHourLow": 0, "creditHourIndicator": "OR", "openSection": true, "linkIdentifier": "A1", "isSectionLinked": true, "subjectCourse": "ELCT254", "faculty": [], "meetingsFaculty": [{"category": "01", "class": "net.hedtech.banner.student.schedule.SectionSessionDecorator", "courseReferenceNumber": "21319", "faculty": [], "meetingTime": {"beginTime": "1200", "building": "CA", "buildingDescription": "Aldred Centre", "campus": "MC", "campusDescription": "Main Campus", "category": "01", "class": "net.hedtech.banner.general.overall.MeetingTimeDecorator", "courseReferenceNumber": "21319", "creditHourSession": 1.5, "endDate": "10/18/2024", "endTime": "1350", "friday": false, "hoursWeek": 2.0, "meetingScheduleType": "L", "meetingType": "CLAS", "meetingTypeDescription": "Class", "monday": false, "room": "CA324", "saturday": false, "startDate": "09/03/2024", "sunday": false, "term": "202420", "thursday": false, "tuesday": true, "wednesday": false}, "term": "202420"}, {"category": "01", "class": "net.hedtech.banner.student.schedule.SectionSessionDecorator", "courseReferenceNumber": "21319", "faculty": [], "meetingTime": {"beginTime": "1200", "building": "CA", "buildingDescription": "Aldred Centre", "campus": "MC", "campusDescription": "Main Campus", "category": "01", "class": "net.hedtech.banner.general.overall.MeetingTimeDecorator", "courseReferenceNumber": "21319", "creditHourSession": 0.0, "endDate": "12/16/2024", "endTime": "1350", "friday": false, "hoursWeek": 2.0, "meetingScheduleType": "L", "meetingType": "CLAS", "meetingTypeDescription": "Class", "monday": false, "room": "CA324", "saturday": false, "startDate": "10/21/2024", "sunday": false, "term": "202420", "thursday": false, "tuesday": true, "wednesday": false}, "term": "202420"}], "reservedSeatSummary": null, "sectionAttributes": [], "instructionalMethod": "IP", "instructionalMethodDescription": "In Person"}, {"id": 141222, "term": "202420", "termDesc": "Fall 2024", "courseReferenceNumber": "21320", "partOfTerm": "1", "courseNumber": "254", "subject": "ELCT", "subjectDescription": "Electrical", "sequenceNumber": "AA", "campusDescription": "Main Campus", "scheduleTypeDescription": "Laboratory", "courseTitle": "Electrical and Controls I", "creditHours": 0, "maximumEnrollment": 16, "enrollment": 0, "seatsAvailable": 16, "waitCapacity": 0, "waitCount": 0, "waitAvailable": 0, "crossList": null, "crossListCapacity": null, "crossListCount": null, "crossListAvailable": null, "creditHourHigh": 1.5, "creditHourLow": 0, "creditHourIndicator": "OR", "openSection": true, "linkIdentifier": "K1", "isSectionLinked": true, "subjectCourse": "ELCT254", "faculty": [], "meetingsFaculty": [{"category": "01", "class": "net.hedtech.banner.student.schedule.SectionSessionDecorator", "courseReferenceNumber": "21320", "faculty": [], "meetingTime": {"beginTime": "1200", "building": "KA", "buildingDescription": "Johnson-Cobbe Energy Centre", "campus": "MC", "campusDescription": "Main Campus", "category": "01", "class": "net.hedtech.banner.general.overall.MeetingTimeDecorator", "courseReferenceNumber": "21320", "creditHourSession": 0.0, "endDate": "10/18/2024", "endTime": "1350", "friday": false, "hoursWeek": 2.0, "meetingScheduleType": "B", "meetingType": "CLAS", "meetingTypeDescription": "Class", "monday": false, "room": "KA221", "saturday": false, "startDate": "09/03/2024", "sunday": false, "term": "202420", "thursday": true, "tuesday": false, "wednesday": false}, "term": "202420"}, {"category": "01", "class": "net.hedtech.banner.student.schedule.SectionSessionDecorator", "courseReferenceNumber": "21320", "faculty": [], "meetingTime": {"beginTime": "1200", "building": "KA", "buildingDescription": "Johnson-Cobbe Energy Centre", "campus": "MC", "campusDescription": "Main Campus", "category": "01", "class": "net.hedtech.banner.general.overall.MeetingTimeDecorator", "courseReferenceNumber": "21320", "creditHourSession": 0.0, "endDate": "10/18/2024", "endTime": "1350", "friday": false, "hoursWeek": 2.0, "meetingScheduleType": "B", "meetingType": "CLAS", "meetingTypeDescription": "Class", "monday": false, "room": "KA217", "saturday": false, "startDate": "09/03/2024", "sunday": false, "term": "202420", "thursday": true, "tuesday": false, "wednesday": false}, "term": "202420"}, {"category": "01", "class": "net.hedtech.banner.student.schedule.SectionSessionDecorator", "courseReferenceNumber": "21320", "faculty": [], "meetingTime": {"beginTime": "1200", "building": "KA", "buildingDescription": "Johnson-Cobbe Energy Centre", "campus": "MC", "campusDescription": "Main Campus", "category": "01", "class": "net.hedtech.banner.general.overall.MeetingTimeDecorator", "courseReferenceNumber": "21320", "creditHourSession": 0.0, "endDate": "12/16/2024", "endTime": "1350", "friday": false, "hoursWeek": 2.0, "meetingScheduleType": "B", "meetingType": "CLAS", "meetingTypeDescription": "Class", "monday": false, "room": "KA012", "saturday": false, "startDate": "10/21/2024", "sunday": false, "term": "202420", "thursday": true, "tuesday": false, "wednesday": false}, "term": "202420"}], "reservedSeatSummary": null, "sectionAttributes": [], "instructionalMethod": "IP", "instructionalMethodDescription": "In Person"}, {"id": 141225, "term": "202420", "termDesc": "Fall 2024", "courseReferenceNumber": "21321", "partOfTerm": "1", "courseNumber": "254", "subject": "ELCT", "subjectDescription": "Electrical", "sequenceNumber": "AAA", "campusDescription": "Main Campus", "scheduleTypeDescription": "Laboratory", "courseTitle": "Electrical and Controls I", "creditHours": 0, "maximumEnrollment": 16, "enrollment": 0, "seatsAvailable": 16, "waitCapacity": 0, "waitCount": 0, "waitAvailable": 0, "crossList": null, "crossListCapacity": null, "crossListCount": null, "crossListAvailable": null, "creditHourHigh": 1.5, "creditHourLow": 0, "creditHourIndicator": "OR", "openSection": true, "linkIdentifier": "K1", "isSectionLinked": true, "subjectCourse": "ELCT254", "faculty": [], "meetingsFaculty": [{"category": "01", "class": "net.hedtech.banner.student.schedule.SectionSessionDecorator", "courseReferenceNumber": "21321", "faculty": [], "meetingTime": {"beginTime": "1300", "building": "KA", "buildingDescription": "Johnson-Cobbe Energy Centre", "campus": "MC", "campusDescription": "Main Campus", "category": "01", "class": "net.hedtech.banner.general.overall.MeetingTimeDecorator", "courseReferenceNumber": "21321", "creditHourSession": 0.0, "endDate": "10/18/2024", "endTime": "1450", "friday": true, "hoursWeek": 2.0, "meetingScheduleType": "B", "meetingType": "CLAS", "meetingTypeDescription": "Class", "monday": false, "room": "KA217", "saturday": false, "startDate": "09/03/2024", "sunday": false, "term": "202420", "thursday": false, "tuesday": false, "wednesday": false}, "term": "202420"}, {"category": "01", "class": "net.hedtech.banner.student.schedule.SectionSessionDecorator", "courseReferenceNumber": "21321", "faculty": [], "meetingTime": {"beginTime": "1300", "building": "KA", "buildingDescription": "Johnson-Cobbe Energy Centre", "campus": "MC", "campusDescription": "Main Campus", "category": "01", "class": "net.hedtech.banner.general.overall.MeetingTimeDecorator", "courseReferenceNumber": "21321", "creditHourSession": 0.0, "endDate": "12/16/2024", "endTime": "1450", "friday": true, "hoursWeek": 2.0, "meetingScheduleType": "B", "meetingType": "CLAS", "meetingTypeDescription": "Class", "monday": false, "room": "KA012", "saturday": false, "startDate": "10/21/2024", "sunday": false, "term": "202420", "thursday": false, "tuesday": false, "wednesday": false}, "term": "202420"}], "reservedSeatSummary": null, "sectionAttributes": [], "instructionalMethod": "IP", "instructionalMethodDescription": "In Person"}, {"id": 141226, "term": "202420", "termDesc": "Fall 2024", "courseReferenceNumber": "21322", "partOfTerm": "1", "courseNumber": "254", "subject": "ELCT", "subjectDescription": "Electrical", "sequenceNumber": "B", "campusDescription": "Main Campus", "scheduleTypeDescription": "Lecture", "courseTitle": "Electrical and Controls I", "creditHours": 1.5, "maximumEnrollment": 32, "enrollment": 0, "seatsAvailable": 32, "waitCapacity": 0, "waitCount": 0, "waitAvailable": 0, "crossList": null, "crossListCapacity": null, "crossListCount": null, "crossListAvailable": null, "creditHourHigh": 1.5, "creditHourLow": 0, "creditHourIndicator": "OR", "openSection": true, "linkIdentifier": "A2", "isSectionLinked": true, "subjectCourse": "ELCT254", "faculty": [], "meetingsFaculty": [{"category": "01", "class": "net.hedtech.banner.student.schedule.SectionSessionDecorator", "courseReferenceNumber": "21322", "faculty": [], "meetingTime": {"beginTime": "1000", "building": "T", "buildingDescription": "Thomas Riley Building", "campus": "MC", "campusDescription": "Main Campus", "category": "01", "class": "net.hedtech.banner.general.overall.MeetingTimeDecorator", "courseReferenceNumber": "21322", "creditHourSession": 0.0, "endDate": "12/16/2024", "endTime": "1150", "friday": false, "hoursWeek": 2.0, "meetingScheduleType": "L", "meetingType": "CLAS", "meetingTypeDescription": "Class", "monday": false, "room": "TT233", "saturday": false, "startDate": "10/21/2024", "sunday": false, "term": "202420", "thursday": false, "tuesday": false, "wednesday": true}, "term": "202420"}, {"category": "01", "class": "net.hedtech.banner.student.schedule.SectionSessionDecorator", "courseReferenceNumber": "21322", "faculty": [], "meetingTime": {"beginTime": "1100", "building": "KA", "buildingDescription": "Johnson-Cobbe Energy Centre", "campus": "MC", "campusDescription": "Main Campus", "category": "01", "class": "net.hedtech.banner.general.overall.MeetingTimeDecorator", "courseReferenceNumber": "21322", "creditHourSession": 1.5, "endDate": "10/18/2024", "endTime": "1250", "friday": false, "hoursWeek": 2.0, "meetingScheduleType": "L", "meetingType": "CLAS", "meetingTypeDescription": "Class", "monday": false, "room": "KA008", "saturday": false, "startDate": "09/03/2024", "sunday": false, "term": "202420", "thursday": false, "tuesday": false, "wednesday": true}, "term": "202420"}], "reservedSeatSummary": null, "sectionAttributes": [], "instructionalMethod": "IP", "instructionalMethodDescription": "In Person"}, {"id": 141227, "term": "202420", "termDesc": "Fall 2024", "courseReferenceNumber": "21323", "partOfTerm": "1", "courseNumber": "254", "subject": "ELCT", "subjectDescription": "Electrical", "sequenceNumber": "BB", "campusDescription": "Main Campus", "scheduleTypeDescription": "Laboratory", "courseTitle": "Electrical and Controls I", "creditHours": 0, "maximumEnrollment": 16, "enrollment": 0, "seatsAvailable": 16, "waitCapacity": 0, "waitCount": 0, "waitAvailable": 0, "crossList": null, "crossListCapacity": null, "crossListCount": null, "crossListAvailable": null, "creditHourHigh": 1.5, "creditHourLow": 0, "creditHourIndicator": "OR", "openSection": true, "linkIdentifier": "K2", "isSectionLinked": true, "subjectCourse": "ELCT254", "faculty": [], "meetingsFaculty": [{"category": "01", "class": "net.hedtech.banner.student.schedule.SectionSessionDecorator", "courseReferenceNumber": "21323", "faculty": [], "meetingTime": {"beginTime": "1300", "building": "KA", "buildingDescription": "Johnson-Cobbe Energy Centre", "campus": "MC", "campusDescription": "Main Campus", "category": "01", "class": "net.hedtech.banner.general.overall.MeetingTimeDecorator", "courseReferenceNumber": "21323", "creditHourSession": 0.0, "endDate": "10/18/2024", "endTime": "1450", "friday": false, "hoursWeek": 2.0, "meetingScheduleType": "B", "meetingType": "CLAS", "meetingTypeDescription": "Class", "monday": false, "room": "KA012", "saturday": false, "startDate": "09/03/2024", "sunday": false, "term": "202420", "thursday": false, "tuesday": true, "wednesday": false}, "term": "202420"}, {"category": "01", "class": "net.hedtech.banner.student.schedule.SectionSessionDecorator", "courseReferenceNumber": "21323", "faculty": [], "meetingTime": {"beginTime": "1300", "building": "KA", "buildingDescription": "Johnson-Cobbe Energy Centre", "campus": "MC", "campusDescription": "Main Campus", "category": "01", "class": "net.hedtech.banner.general.overall.MeetingTimeDecorator", "courseReferenceNumber": "21323", "creditHourSession": 0.0, "endDate": "12/16/2024", "endTime": "1450", "friday": false, "hoursWeek": 2.0, "meetingScheduleType": "B", "meetingType": "CLAS", "meetingTypeDescription": "Class", "monday": false, "room": "KA217", "saturday": false, "startDate": "10/21/2024", "sunday": false, "term": "202420", "thursday": false, "tuesday": true, "wednesday": false}, "term": "202420"}], "reservedSeatSummary": null, "sectionAttributes": [], "instructionalMethod": "IP", "instructionalMethodDescription": "In Person"}, {"id": 141228, "term": "202420", "termDesc": "Fall 2024", "courseReferenceNumber": "21324", "partOfTerm": "1", "courseNumber": "254", "subject": "ELCT", "subjectDescription": "Electrical", "sequenceNumber": "BBB", "campusDescription": "Main Campus", "scheduleTypeDescription": "Laboratory", "courseTitle": "Electrical and Controls I", "creditHours": 0, "maximumEnrollment": 16, "enrollment": 0, "seatsAvailable": 16, "waitCapacity": 0, "waitCount": 0, "waitAvailable": 0, "crossList": null, "crossListCapacity": null, "crossListCount": null, "crossListAvailable": null, "creditHourHigh": 1.5, "creditHourLow": 0, "creditHourIndicator": "OR", "openSection": true, "linkIdentifier": "K2", "isSectionLinked": true, "subjectCourse": "ELCT254", "faculty": [], "meetingsFaculty": [{"category": "01", "class": "net.hedtech.banner.student.schedule.SectionSessionDecorator", "courseReferenceNumber": "21324", "faculty": [], "meetingTime": {"beginTime": "0800", "building": "KA", "buildingDescription": "Johnson-Cobbe Energy Centre", "campus": "MC", "campusDescription": "Main Campus", "category": "01", "class": "net.hedtech.banner.general.overall.MeetingTimeDecorator", "courseReferenceNumber": "21324", "creditHourSession": 0.0, "endDate": "10/18/2024", "endTime": "0950", "friday": false, "hoursWeek": 2.0, "meetingScheduleType": "B", "meetingType": "CLAS", "meetingTypeDescription": "Class", "monday": false, "room": "KA012", "saturday": false, "startDate": "09/03/2024", "sunday": false, "term": "202420", "thursday": false, "tuesday": false, "wednesday": true}, "term": "202420"}, {"category": "01", "class": "net.hedtech.banner.student.schedule.SectionSessionDecorator", "courseReferenceNumber": "21324", "faculty": [], "meetingTime": {"beginTime": "0800", "building": "KA", "buildingDescription": "Johnson-Cobbe Energy Centre", "campus": "MC", "campusDescription": "Main Campus", "category": "01", "class": "net.hedtech.banner.general.overall.MeetingTimeDecorator", "courseReferenceNumber": "21324", "creditHourSession": 0.0, "endDate": "12/16/2024", "endTime": "0950", "friday": false, "hoursWeek": 2.0, "meetingScheduleType": "B", "meetingType": "CLAS", "meetingTypeDescription": "Class", "monday": false, "room": "KA221", "saturday": false, "startDate": "10/21/2024", "sunday": false, "term": "202420", "thursday": false, "tuesday": false, "wednesday": true}, "term": "202420"}, {"category": "01", "class": "net.hedtech.banner.student.schedule.SectionSessionDecorator", "courseReferenceNumber": "21324", "faculty": [], "meetingTime": {"beginTime": "0800", "building": "KA", "buildingDescription": "Johnson-Cobbe Energy Centre", "campus": "MC", "campusDescription": "Main Campus", "category": "01", "class": "net.hedtech.banner.general.overall.MeetingTimeDecorator", "courseReferenceNumber": "21324", "creditHourSession": 0.0, "endDate": "12/16/2024", "endTime": "0950", "friday": false, "hoursWeek": 2.0, "meetingScheduleType": "B", "meetingType": "CLAS", "meetingTypeDescription": "Class", "monday": false, "room": "KA217", "saturday": false, "startDate": "10/21/2024", "sunday": false, "term": "202420", "thursday": false, "tuesday": false, "wednesday": true}, "term": "202420"}], "reservedSeatSummary": null, "sectionAttributes": [], "instructionalMethod": "IP", "instructionalMethodDescription": "In Person"}, {"id": 142471, "term": "202420", "termDesc": "Fall 2024", "courseReferenceNumber": "21325", "partOfTerm": "1", "courseNumber": "254", "subject": "ELCT", "subjectDescription": "Electrical", "sequenceNumber": "C", "campusDescription": "Main Campus", "scheduleTypeDescription": "Lecture", "courseTitle": "Electrical and Controls I", "creditHours": 1.5, "maximumEnrollment": 32, "enrollment": 0, "seatsAvailable": 32, "waitCapacity": 0, "waitCount": 0, "waitAvailable": 0, "crossList": null, "crossListCapacity": null, "crossListCount": null, "crossListAvailable": null, "creditHourHigh": 1.5, "creditHourLow": 0, "creditHourIndicator": "OR", "openSection": true, "linkIdentifier": "A3", "isSectionLinked": true, "subjectCourse": "ELCT254", "faculty": [], "meetingsFaculty": [{"category": "01", "class": "net.hedtech.banner.student.schedule.SectionSessionDecorator", "courseReferenceNumber": "21325", "faculty": [], "meetingTime": {"beginTime": "1200", "building": "N", "buildingDescription": "Senator Burns Building", "campus": "MC", "campusDescription": "Main Campus", "category": "01", "class": "net.hedtech.banner.general.overall.MeetingTimeDecorator", "courseReferenceNumber": "21325", "creditHourSession": 1.5, "endDate": "10/18/2024", "endTime": "1350", "friday": false, "hoursWeek": 2.0, "meetingScheduleType": "L", "meetingType": "CLAS", "meetingTypeDescription": "Class", "monday": true, "room": "NR419", "saturday": false, "startDate": "09/03/2024", "sunday": false, "term": "202420", "thursday": false, "tuesday": false, "wednesday": false}, "term": "202420"}, {"category": "01", "class": "net.hedtech.banner.student.schedule.SectionSessionDecorator", "courseReferenceNumber": "21325", "faculty": [], "meetingTime": {"beginTime": "1200", "building": "KA", "buildingDescription": "Johnson-Cobbe Energy Centre", "campus": "MC", "campusDescription": "Main Campus", "category": "01", "class": "net.hedtech.banner.general.overall.MeetingTimeDecorator", "courseReferenceNumber": "21325", "creditHourSession": 0.0, "endDate": "12/16/2024", "endTime": "1350", "friday": false, "hoursWeek": 2.0, "meetingScheduleType": "L", "meetingType": "CLAS", "meetingTypeDescription": "Class", "monday": true, "room": "KA226", "saturday": false, "startDate": "10/21/2024", "sunday": false, "term": "202420", "thursday": false, "tuesday": false, "wednesday": false}, "term": "202420"}], "reservedSeatSummary": null, "sectionAttributes": [], "instructionalMethod": "IP", "instructionalMethodDescription": "In Person"}, {"id": 142470, "term": "202420", "termDesc": "Fall 2024", "courseReferenceNumber": "21326", "partOfTerm": "1", "courseNumber": "254", "subject": "ELCT", "subjectDescription": "Electrical", "sequenceNumber": "CC", "campusDescription": "Main Campus", "scheduleTypeDescription": "Laboratory", "courseTitle": "Electrical and Controls I", "creditHours": 0, "maximumEnrollment": 16, "enrollment": 0, "seatsAvailable": 16, "waitCapacity": 0, "waitCount": 0, "waitAvailable": 0, "crossList": null, "crossListCapacity": null, "crossListCount": null, "crossListAvailable": null, "creditHourHigh": 1.5, "creditHourLow": 0, "creditHourIndicator": "OR", "openSection": true, "linkIdentifier": "K3", "isSectionLinked": true, "subjectCourse": "ELCT254", "faculty": [], "meetingsFaculty": [{"category": "01", "class": "net.hedtech.banner.student.schedule.SectionSessionDecorator", "courseReferenceNumber": "21326", "faculty": [], "meetingTime": {"beginTime": "0800", "building": "KA", "buildingDescription": "Johnson-Cobbe Energy Centre", "campus": "MC", "campusDescription": "Main Campus", "category": "01", "class": "net.hedtech.banner.general.overall.MeetingTimeDecorator", "courseReferenceNumber": "21326", "creditHourSession": 0.0, "endDate": "12/16/2024", "endTime": "0950", "friday": false, "hoursWeek": 2.0, "meetingScheduleType": "B", "meetingType": "CLAS", "meetingTypeDescription": "Class", "monday": true, "room": "KA012", "saturday": false, "startDate": "10/21/2024", "sunday": false, "term": "202420", "thursday": false, "tuesday": false, "wednesday": false}, "term": "202420"}, {"category": "01", "class": "net.hedtech.banner.student.schedule.SectionSessionDecorator", "courseReferenceNumber": "21326", "faculty": [], "meetingTime": {"beginTime": "0800", "building": "KA", "buildingDescription": "Johnson-Cobbe Energy Centre", "campus": "MC", "campusDescription": "Main Campus", "category": "01", "class": "net.hedtech.banner.general.overall.MeetingTimeDecorator", "courseReferenceNumber": "21326", "creditHourSession": 0.0, "endDate": "10/18/2024", "endTime": "0950", "friday": false, "hoursWeek": 2.0, "meetingScheduleType": "B", "meetingType": "CLAS", "meetingTypeDescription": "Class", "monday": true, "room": "KA221", "saturday": false, "startDate": "09/03/2024", "sunday": false, "term": "202420", "thursday": false, "tuesday": false, "wednesday": false}, "term": "202420"}, {"category": "01", "class": "net.hedtech.banner.student.schedule.SectionSessionDecorator", "courseReferenceNumber": "21326", "faculty": [], "meetingTime": {"beginTime": "0800", "building": "KA", "buildingDescription": "Johnson-Cobbe Energy Centre", "campus": "MC", "campusDescription": "Main Campus", "category": "01", "class": "net.hedtech.banner.general.overall.MeetingTimeDecorator", "courseReferenceNumber": "21326", "creditHourSession": 0.0, "endDate": "10/18/2024", "endTime": "0950", "friday": false, "hoursWeek": 2.0, "meetingScheduleType": "B", "meetingType": "CLAS", "meetingTypeDescription": "Class", "monday": true, "room": "KA217", "saturday": false, "startDate": "09/03/2024", "sunday": false, "term": "202420", "thursday": false, "tuesday": false, "wednesday": false}, "term": "202420"}], "reservedSeatSummary": null, "sectionAttributes": [], "instructionalMethod": "IP", "instructionalMethodDescription": "In Person"}, {"id": 142472, "term": "202420", "termDesc": "Fall 2024", "courseReferenceNumber": "21327", "partOfTerm": "1", "courseNumber": "254", "subject": "ELCT", "subjectDescription": "Electrical", "sequenceNumber": "CCC", "campusDescription": "Main Campus", "scheduleTypeDescription": "Laboratory", "courseTitle": "Electrical and Controls I", "creditHours": 0, "maximumEnrollment": 16, "enrollment": 0, "seatsAvailable": 16, "waitCapacity": 0, "waitCount": 0, "waitAvailable": 0, "crossList": null, "crossListCapacity": null, "crossListCount": null, "crossListAvailable": null, "creditHourHigh": 1.5, "creditHourLow": 0, "creditHourIndicator": "OR", "openSection": true, "linkIdentifier": "K3", "isSectionLinked": true, "subjectCourse": "ELCT254", "faculty": [], "meetingsFaculty": [{"category": "01", "class": "net.hedtech.banner.student.schedule.SectionSessionDecorator", "courseReferenceNumber": "21327", "faculty": [], "meetingTime": {"beginTime": "1400", "building": "KA", "buildingDescription": "Johnson-Cobbe Energy Centre", "campus": "MC", "campusDescription": "Main Campus", "category": "01", "class": "net.hedtech.banner.general.overall.MeetingTimeDecorator", "courseReferenceNumber": "21327", "creditHourSession": 0.0, "endDate": "12/16/2024", "endTime": "1550", "friday": false, "hoursWeek": 2.0, "meetingScheduleType": "B", "meetingType": "CLAS", "meetingTypeDescription": "Class", "monday": false, "room": "KA012", "saturday": false, "startDate": "10/21/2024", "sunday": false, "term": "202420", "thursday": false, "tuesday": true, "wednesday": false}, "term": "202420"}, {"category": "01", "class": "net.hedtech.banner.student.schedule.SectionSessionDecorator", "courseReferenceNumber": "21327", "faculty": [], "meetingTime": {"beginTime": "1400", "building": "KA", "buildingDescription": "Johnson-Cobbe Energy Centre", "campus": "MC", "campusDescription": "Main Campus", "category": "01", "class": "net.hedtech.banner.general.overall.MeetingTimeDecorator", "courseReferenceNumber": "21327", "creditHourSession": 0.0, "endDate": "10/18/2024", "endTime": "1550", "friday": false, "hoursWeek": 2.0, "meetingScheduleType": "B", "meetingType": "CLAS", "meetingTypeDescription": "Class", "monday": false, "room": "KA217", "saturday": false, "startDate": "09/03/2024", "sunday": false, "term": "202420", "thursday": false, "tuesday": true, "wednesday": false}, "term": "202420"}], "reservedSeatSummary": null, "sectionAttributes": [], "instructionalMethod": "IP", "instructionalMethodDescription": "In Person"}, {"id": 143194, "term": "202420", "termDesc": "Fall 2024", "courseReferenceNumber": "21328", "partOfTerm": "1", "courseNumber": "254", "subject": "ELCT", "subjectDescription": "Electrical", "sequenceNumber": "D", "campusDescription": "Main Campus", "scheduleTypeDescription": "Lecture", "courseTitle": "Electrical and Controls I", "creditHours": 1.5, "maximumEnrollment": 32, "enrollment": 0, "seatsAvailable": 32, "waitCapacity": 0, "waitCount": 0, "waitAvailable": 0, "crossList": null, "crossListCapacity": null, "crossListCount": null, "crossListAvailable": null, "creditHourHigh": 1.5, "creditHourLow": 0, "creditHourIndicator": "OR", "openSection": true, "linkIdentifier": "A4", "isSectionLinked": true, "subjectCourse": "ELCT254", "faculty": [], "meetingsFaculty": [{"category": "01", "class": "net.hedtech.banner.student.schedule.SectionSessionDecorator", "courseReferenceNumber": "21328", "faculty": [], "meetingTime": {"beginTime": "1300", "building": "KA", "buildingDescription": "Johnson-Cobbe Energy Centre", "campus": "MC", "campusDescription": "Main Campus", "category": "01", "class": "net.hedtech.banner.general.overall.MeetingTimeDecorator", "courseReferenceNumber": "21328", "creditHourSession": 1.5, "endDate": "10/18/2024", "endTime": "1450", "friday": false, "hoursWeek": 2.0, "meetingScheduleType": "L", "meetingType": "CLAS", "meetingTypeDescription": "Class", "monday": true, "room": "KA223", "saturday": false, "startDate": "09/03/2024", "sunday": false, "term": "202420", "thursday": false, "tuesday": false, "wednesday": false}, "term": "202420"}, {"category": "01", "class": "net.hedtech.banner.student.schedule.SectionSessionDecorator", "courseReferenceNumber": "21328", "faculty": [], "meetingTime": {"beginTime": "1300", "building": "KA", "buildingDescription": "Johnson-Cobbe Energy Centre", "campus": "MC", "campusDescription": "Main Campus", "category": "01", "class": "net.hedtech.banner.general.overall.MeetingTimeDecorator", "courseReferenceNumber": "21328", "creditHourSession": 0.0, "endDate": "12/16/2024", "endTime": "1450", "friday": false, "hoursWeek": 2.0, "meetingScheduleType": "L", "meetingType": "CLAS", "meetingTypeDescription": "Class", "monday": true, "room": "KA223", "saturday": false, "startDate": "10/21/2024", "sunday": false, "term": "202420", "thursday": false, "tuesday": false, "wednesday": false}, "term": "202420"}], "reservedSeatSummary": null, "sectionAttributes": [], "instructionalMethod": "IP", "instructionalMethodDescription": "In Person"}, {"id": 143195, "term": "202420", "termDesc": "Fall 2024", "courseReferenceNumber": "21329", "partOfTerm": "1", "courseNumber": "254", "subject": "ELCT", "subjectDescription": "Electrical", "sequenceNumber": "DD", "campusDescription": "Main Campus", "scheduleTypeDescription": "Laboratory", "courseTitle": "Electrical and Controls I", "creditHours": 0, "maximumEnrollment": 16, "enrollment": 0, "seatsAvailable": 16, "waitCapacity": 0, "waitCount": 0, "waitAvailable": 0, "crossList": null, "crossListCapacity": null, "crossListCount": null, "crossListAvailable": null, "creditHourHigh": 1.5, "creditHourLow": 0, "creditHourIndicator": "OR", "openSection": true, "linkIdentifier": "K4", "isSectionLinked": true, "subjectCourse": "ELCT254", "faculty": [], "meetingsFaculty": [{"category": "01", "class": "net.hedtech.banner.student.schedule.SectionSessionDecorator", "courseReferenceNumber": "21329", "faculty": [], "meetingTime": {"beginTime": "1500", "building": "KA", "buildingDescription": "Johnson-Cobbe Energy Centre", "campus": "MC", "campusDescription": "Main Campus", "category": "01", "class": "net.hedtech.banner.general.overall.MeetingTimeDecorator", "courseReferenceNumber": "21329", "creditHourSession": 0.0, "endDate": "10/18/2024", "endTime": "1650", "friday": false, "hoursWeek": 2.0, "meetingScheduleType": "B", "meetingType": "CLAS", "meetingTypeDescription": "Class", "monday": false, "room": "KA012", "saturday": false, "startDate": "09/03/2024", "sunday": false, "term": "202420", "thursday": false, "tuesday": true, "wednesday": false}, "term": "202420"}, {"category": "01", "class": "net.hedtech.banner.student.schedule.SectionSessionDecorator", "courseReferenceNumber": "21329", "faculty": [], "meetingTime": {"beginTime": "1500", "building": "KA", "buildingDescription": "Johnson-Cobbe Energy Centre", "campus": "MC", "campusDescription": "Main Campus", "category": "01", "class": "net.hedtech.banner.general.overall.MeetingTimeDecorator", "courseReferenceNumber": "21329", "creditHourSession": 0.0, "endDate": "12/16/2024", "endTime": "1650", "friday": false, "hoursWeek": 2.0, "meetingScheduleType": "B", "meetingType": "CLAS", "meetingTypeDescription": "Class", "monday": false, "room": "KA217", "saturday": false, "startDate": "10/21/2024", "sunday": false, "term": "202420", "thursday": false, "tuesday": true, "wednesday": false}, "term": "202420"}], "reservedSeatSummary": null, "sectionAttributes": [], "instructionalMethod": "IP", "instructionalMethodDescription": "In Person"}, {"id": 143193, "term": "202420", "termDesc": "Fall 2024", "courseReferenceNumber": "21330", "partOfTerm": "1", "courseNumber": "254", "subject": "ELCT", "subjectDescription": "Electrical", "sequenceNumber": "DDD", "campusDescription": "Main Campus", "scheduleTypeDescription": "Laboratory", "courseTitle": "Electrical and Controls I", "creditHours": 0, "maximumEnrollment": 16, "enrollment": 0, "seatsAvailable": 16, "waitCapacity": 0, "waitCount": 0, "waitAvailable": 0, "crossList": null, "crossListCapacity": null, "crossListCount": null, "crossListAvailable": null, "creditHourHigh": 1.5, "creditHourLow": 0, "creditHourIndicator": "OR", "openSection": true, "linkIdentifier": "K4", "isSectionLinked": true, "subjectCourse": "ELCT254", "faculty": [], "meetingsFaculty": [{"category": "01", "class": "net.hedtech.banner.student.schedule.SectionSessionDecorator", "courseReferenceNumber": "21330", "faculty": [], "meetingTime": {"beginTime": "1300", "building": "KA", "buildingDescription": "Johnson-Cobbe Energy Centre", "campus": "MC", "campusDescription": "Main Campus", "category": "01", "class": "net.hedtech.banner.general.overall.MeetingTimeDecorator", "courseReferenceNumber": "21330", "creditHourSession": 0.0, "endDate": "10/18/2024", "endTime": "1450", "friday": false, "hoursWeek": 2.0, "meetingScheduleType": "B", "meetingType": "CLAS", "meetingTypeDescription": "Class", "monday": false, "room": "KA012", "saturday": false, "startDate": "09/03/2024", "sunday": false, "term": "202420", "thursday": true, "tuesday": false, "wednesday": false}, "term": "202420"}, {"category": "01", "class": "net.hedtech.banner.student.schedule.SectionSessionDecorator", "courseReferenceNumber": "21330", "faculty": [], "meetingTime": {"beginTime": "1300", "building": "KA", "buildingDescription": "Johnson-Cobbe Energy Centre", "campus": "MC", "campusDescription": "Main Campus", "category": "01", "class": "net.hedtech.banner.general.overall.MeetingTimeDecorator", "courseReferenceNumber": "21330", "creditHourSession": 0.0, "endDate": "12/16/2024", "endTime": "1450", "friday": false, "hoursWeek": 2.0, "meetingScheduleType": "B", "meetingType": "CLAS", "meetingTypeDescription": "Class", "monday": false, "room": "KA221", "saturday": false, "startDate": "10/21/2024", "sunday": false, "term": "202420", "thursday": true, "tuesday": false, "wednesday": false}, "term": "202420"}, {"category": "01", "class": "net.hedtech.banner.student.schedule.SectionSessionDecorator", "courseReferenceNumber": "21330", "faculty": [], "meetingTime": {"beginTime": "1300", "building": "KA", "buildingDescription": "Johnson-Cobbe Energy Centre", "campus": "MC", "campusDescription": "Main Campus", "category": "01", "class": "net.hedtech.banner.general.overall.MeetingTimeDecorator", "courseReferenceNumber": "21330", "creditHourSession": 0.0, "endDate": "12/16/2024", "endTime": "1450", "friday": false, "hoursWeek": 2.0, "meetingScheduleType": "B", "meetingType": "CLAS", "meetingTypeDescription": "Class", "monday": false, "room": "KA217", "saturday": false, "startDate": "10/21/2024", "sunday": false, "term": "202420", "thursday": true, "tuesday": false, "wednesday": false}, "term": "202420"}], "reservedSeatSummary": null, "sectionAttributes": [], "instructionalMethod": "IP", "instructionalMethodDescription": "In Person"}, {"id": 140723, "term": "202420", "termDesc": "Fall 2024", "courseReferenceNumber": "21331", "partOfTerm": "1", "courseNumber": "304", "subject": "ELCT", "subjectDescription": "Electrical", "sequenceNumber": "A", "campusDescription": "Main Campus", "scheduleTypeDescription": "Lecture", "courseTitle": "Electrical and Controls II", "creditHours": 3, "maximumEnrollment": 32, "enrollment": 0, "seatsAvailable": 32, "waitCapacity": 0, "waitCount": 0, "waitAvailable": 0, "crossList": null, "crossListCapacity": null, "crossListCount": null, "crossListAvailable": null, "creditHourHigh": 3, "creditHourLow": 0, "creditHourIndicator": "OR", "openSection": true, "linkIdentifier": "A1", "isSectionLinked": true, "subjectCourse": "ELCT304", "faculty": [], "meetingsFaculty": [{"category": "01", "class": "net.hedtech.banner.student.schedule.SectionSessionDecorator", "courseReferenceNumber": "21331", "faculty": [], "meetingTime": {"beginTime": "0900", "building": "CA", "buildingDescription": "Aldred Centre", "campus": "MC", "campusDescription": "Main Campus", "category": "01", "class": "net.hedtech.banner.general.overall.MeetingTimeDecorator", "courseReferenceNumber": "21331", "creditHourSession": 3.0, "endDate": "12/16/2024", "endTime": "0950", "friday": true, "hoursWeek": 1.0, "meetingScheduleType": "L", "meetingType": "CLAS", "meetingTypeDescription": "Class", "monday": false, "room": "CA324", "saturday": false, "startDate": "09/03/2024", "sunday": false, "term": "202420", "thursday": false, "tuesday": false, "wednesday": false}, "term": "202420"}, {"category": "01", "class": "net.hedtech.banner.student.schedule.SectionSessionDecorator", "courseReferenceNumber": "21331", "faculty": [], "meetingTime": {"beginTime": "1100", "building": "KA", "buildingDescription": "Johnson-Cobbe Energy Centre", "campus": "MC", "campusDescription": "Main Campus", "category": "01", "class": "net.hedtech.banner.general.overall.MeetingTimeDecorator", "courseReferenceNumber": "21331", "creditHourSession": 0.0, "endDate": "12/16/2024", "endTime": "1250", "friday": false, "hoursWeek": 2.0, "meetingScheduleType": "L", "meetingType": "CLAS", "meetingTypeDescription": "Class", "monday": false, "room": "KA310", "saturday": false, "startDate": "09/03/2024", "sunday": false, "term": "202420", "thursday": false, "tuesday": true, "wednesday": false}, "term": "202420"}], "reservedSeatSummary": null, "sectionAttributes": [], "instructionalMethod": "IP", "instructionalMethodDescription": "In Person"}, {"id": 140724, "term": "202420", "termDesc": "Fall 2024", "courseReferenceNumber": "21332", "partOfTerm": "1", "courseNumber": "304", "subject": "ELCT", "subjectDescription": "Electrical", "sequenceNumber": "AA", "campusDescription": "Main Campus", "scheduleTypeDescription": "Laboratory", "courseTitle": "Electrical and Controls II", "creditHours": 0, "maximumEnrollment": 16, "enrollment": 0, "seatsAvailable": 16, "waitCapacity": 0, "waitCount": 0, "waitAvailable": 0, "crossList": null, "crossListCapacity": null, "crossListCount": null, "crossListAvailable": null, "creditHourHigh": 3, "creditHourLow": 0, "creditHourIndicator": "OR", "openSection": true, "linkIdentifier": "K1", "isSectionLinked": true, "subjectCourse": "ELCT304", "faculty": [], "meetingsFaculty": [{"category": "01", "class": "net.hedtech.banner.student.schedule.SectionSessionDecorator", "courseReferenceNumber": "21332", "faculty": [], "meetingTime": {"beginTime": "0800", "building": "KA", "buildingDescription": "Johnson-Cobbe Energy Centre", "campus": "MC", "campusDescription": "Main Campus", "category": "01", "class": "net.hedtech.banner.general.overall.MeetingTimeDecorator", "courseReferenceNumber": "21332", "creditHourSession": 0.0, "endDate": "11/22/2024", "endTime": "0950", "friday": false, "hoursWeek": 2.0, "meetingScheduleType": "B", "meetingType": "CLAS", "meetingTypeDescription": "Class", "monday": true, "room": "KA217", "saturday": false, "startDate": "10/21/2024", "sunday": false, "term": "202420", "thursday": false, "tuesday": false, "wednesday": false}, "term": "202420"}, {"category": "01", "class": "net.hedtech.banner.student.schedule.SectionSessionDecorator", "courseReferenceNumber": "21332", "faculty": [], "meetingTime": {"beginTime": "0800", "building": "KA", "buildingDescription": "Johnson-Cobbe Energy Centre", "campus": "MC", "campusDescription": "Main Campus", "category": "01", "class": "net.hedtech.banner.general.overall.MeetingTimeDecorator", "courseReferenceNumber": "21332", "creditHourSession": 0.0, "endDate": "11/22/2024", "endTime": "0950", "friday": false, "hoursWeek": 2.0, "meetingScheduleType": "B", "meetingType": "CLAS", "meetingTypeDescription": "Class", "monday": true, "room": "KA221", "saturday": false, "startDate": "10/21/2024", "sunday": false, "term": "202420", "thursday": false, "tuesday": false, "wednesday": false}, "term": "202420"}, {"category": "01", "class": "net.hedtech.banner.student.schedule.SectionSessionDecorator", "courseReferenceNumber": "21332", "faculty": [], "meetingTime": {"beginTime": "0800", "building": "KA", "buildingDescription": "Johnson-Cobbe Energy Centre", "campus": "MC", "campusDescription": "Main Campus", "category": "01", "class": "net.hedtech.banner.general.overall.MeetingTimeDecorator", "courseReferenceNumber": "21332", "creditHourSession": 0.0, "endDate": "12/06/2024", "endTime": "0950", "friday": false, "hoursWeek": 2.0, "meetingScheduleType": "B", "meetingType": "CLAS", "meetingTypeDescription": "Class", "monday": true, "room": "KA123", "saturday": false, "startDate": "11/25/2024", "sunday": false, "term": "202420", "thursday": false, "tuesday": false, "wednesday": false}, "term": "202420"}, {"category": "01", "class": "net.hedtech.banner.student.schedule.SectionSessionDecorator", "courseReferenceNumber": "21332", "faculty": [], "meetingTime": {"beginTime": "0800", "building": "KA", "buildingDescription": "Johnson-Cobbe Energy Centre", "campus": "MC", "campusDescription": "Main Campus", "category": "01", "class": "net.hedtech.banner.general.overall.MeetingTimeDecorator", "courseReferenceNumber": "21332", "creditHourSession": 0.0, "endDate": "10/18/2024", "endTime": "0950", "friday": false, "hoursWeek": 2.0, "meetingScheduleType": "B", "meetingType": "CLAS", "meetingTypeDescription": "Class", "monday": true, "room": "KA209", "saturday": false, "startDate": "09/03/2024", "sunday": false, "term": "202420", "thursday": false, "tuesday": false, "wednesday": false}, "term": "202420"}], "reservedSeatSummary": null, "sectionAttributes": [], "instructionalMethod": "IP", "instructionalMethodDescription": "In Person"}, {"id": 142204, "term": "202420", "termDesc": "Fall 2024", "courseReferenceNumber": "21333", "partOfTerm": "1", "courseNumber": "304", "subject": "ELCT", "subjectDescription": "Electrical", "sequenceNumber": "AAA", "campusDescription": "Main Campus", "scheduleTypeDescription": "Laboratory", "courseTitle": "Electrical and Controls II", "creditHours": 0, "maximumEnrollment": 16, "enrollment": 0, "seatsAvailable": 16, "waitCapacity": 0, "waitCount": 0, "waitAvailable": 0, "crossList": null, "crossListCapacity": null, "crossListCount": null, "crossListAvailable": null, "creditHourHigh": 3, "creditHourLow": 0, "creditHourIndicator": "OR", "openSection": true, "linkIdentifier": "K1", "isSectionLinked": true, "subjectCourse": "ELCT304", "faculty": [], "meetingsFaculty": [{"category": "01", "class": "net.hedtech.banner.student.schedule.SectionSessionDecorator", "courseReferenceNumber": "21333", "faculty": [], "meetingTime": {"beginTime": "1500", "building": "KA", "buildingDescription": "Johnson-Cobbe Energy Centre", "campus": "MC", "campusDescription": "Main Campus", "category": "01", "class": "net.hedtech.banner.general.overall.MeetingTimeDecorator", "courseReferenceNumber": "21333", "creditHourSession": 0.0, "endDate": "11/22/2024", "endTime": "1650", "friday": false, "hoursWeek": 2.0, "meetingScheduleType": "B", "meetingType": "CLAS", "meetingTypeDescription": "Class", "monday": false, "room": "KA217", "saturday": false, "startDate": "10/21/2024", "sunday": false, "term": "202420", "thursday": true, "tuesday": false, "wednesday": false}, "term": "202420"}, {"category": "01", "class": "net.hedtech.banner.student.schedule.SectionSessionDecorator", "courseReferenceNumber": "21333", "faculty": [], "meetingTime": {"beginTime": "1500", "building": "KA", "buildingDescription": "Johnson-Cobbe Energy Centre", "campus": "MC", "campusDescription": "Main Campus", "category": "01", "class": "net.hedtech.banner.general.overall.MeetingTimeDecorator", "courseReferenceNumber": "21333", "creditHourSession": 0.0, "endDate": "11/22/2024", "endTime": "1650", "friday": false, "hoursWeek": 2.0, "meetingScheduleType": "B", "meetingType": "CLAS", "meetingTypeDescription": "Class", "monday": false, "room": "KA221", "saturday": false, "startDate": "10/21/2024", "sunday": false, "term": "202420", "thursday": true, "tuesday": false, "wednesday": false}, "term": "202420"}, {"category": "01", "class": "net.hedtech.banner.student.schedule.SectionSessionDecorator", "courseReferenceNumber": "21333", "faculty": [], "meetingTime": {"beginTime": "1500", "building": "KA", "buildingDescription": "Johnson-Cobbe Energy Centre", "campus": "MC", "campusDescription": "Main Campus", "category": "01", "class": "net.hedtech.banner.general.overall.MeetingTimeDecorator", "courseReferenceNumber": "21333", "creditHourSession": 0.0, "endDate": "10/18/2024", "endTime": "1650", "friday": false, "hoursWeek": 2.0, "meetingScheduleType": "B", "meetingType": "CLAS", "meetingTypeDescription": "Class", "monday": false, "room": "KA209", "saturday": false, "startDate": "09/03/2024", "sunday": false, "term": "202420", "thursday": true, "tuesday": false, "wednesday": false}, "term": "202420"}, {"category": "01", "class": "net.hedtech.banner.student.schedule.SectionSessionDecorator", "courseReferenceNumber": "21333", "faculty": [], "meetingTime": {"beginTime": "1500", "building": "KA", "buildingDescription": "Johnson-Cobbe Energy Centre", "campus": "MC", "campusDescription": "Main Campus", "category": "01", "class": "net.hedtech.banner.general.overall.MeetingTimeDecorator", "courseReferenceNumber": "21333", "creditHourSession": 0.0, "endDate": "12/06/2024", "endTime": "1650", "friday": false, "hoursWeek": 2.0, "meetingScheduleType": "B", "meetingType": "CLAS", "meetingTypeDescription": "Class", "monday": false, "room": "KA123", "saturday": false, "startDate": "11/25/2024", "sunday": false, "term": "202420", "thursday": true, "tuesday": false, "wednesday": false}, "term": "202420"}], "reservedSeatSummary": null, "sectionAttributes": [], "instructionalMethod": "IP", "instructionalMethodDescription": "In Person"}, {"id": 140725, "term": "202420", "termDesc": "Fall 2024", "courseReferenceNumber": "21334", "partOfTerm": "1", "courseNumber": "304", "subject": "ELCT", "subjectDescription": "Electrical", "sequenceNumber": "B", "campusDescription": "Main Campus", "scheduleTypeDescription": "Lecture", "courseTitle": "Electrical and Controls II", "creditHours": 3, "maximumEnrollment": 32, "enrollment": 0, "seatsAvailable": 32, "waitCapacity": 0, "waitCount": 0, "waitAvailable": 0, "crossList": null, "crossListCapacity": null, "crossListCount": null, "crossListAvailable": null, "creditHourHigh": 3, "creditHourLow": 0, "creditHourIndicator": "OR", "openSection": true, "linkIdentifier": "A2", "isSectionLinked": true, "subjectCourse": "ELCT304", "faculty": [], "meetingsFaculty": [{"category": "01", "class": "net.hedtech.banner.student.schedule.SectionSessionDecorator", "courseReferenceNumber": "21334", "faculty": [], "meetingTime": {"beginTime": "0800", "building": "CA", "buildingDescription": "Aldred Centre", "campus": "MC", "campusDescription": "Main Campus", "category": "01", "class": "net.hedtech.banner.general.overall.MeetingTimeDecorator", "courseReferenceNumber": "21334", "creditHourSession": 3.0, "endDate": "12/16/2024", "endTime": "0850", "friday": true, "hoursWeek": 1.0, "meetingScheduleType": "L", "meetingType": "CLAS", "meetingTypeDescription": "Class", "monday": false, "room": "CA324", "saturday": false, "startDate": "09/03/2024", "sunday": false, "term": "202420", "thursday": false, "tuesday": false, "wednesday": false}, "term": "202420"}, {"category": "01", "class": "net.hedtech.banner.student.schedule.SectionSessionDecorator", "courseReferenceNumber": "21334", "faculty": [], "meetingTime": {"beginTime": "1000", "building": "KA", "buildingDescription": "Johnson-Cobbe Energy Centre", "campus": "MC", "campusDescription": "Main Campus", "category": "01", "class": "net.hedtech.banner.general.overall.MeetingTimeDecorator", "courseReferenceNumber": "21334", "creditHourSession": 0.0, "endDate": "12/16/2024", "endTime": "1150", "friday": false, "hoursWeek": 2.0, "meetingScheduleType": "L", "meetingType": "CLAS", "meetingTypeDescription": "Class", "monday": false, "room": "KA337", "saturday": false, "startDate": "09/03/2024", "sunday": false, "term": "202420", "thursday": false, "tuesday": false, "wednesday": true}, "term": "202420"}], "reservedSeatSummary": null, "sectionAttributes": [], "instructionalMethod": "IP", "instructionalMethodDescription": "In Person"}, {"id": 140726, "term": "202420", "termDesc": "Fall 2024", "courseReferenceNumber": "21335", "partOfTerm": "1", "courseNumber": "304", "subject": "ELCT", "subjectDescription": "Electrical", "sequenceNumber": "BB", "campusDescription": "Main Campus", "scheduleTypeDescription": "Laboratory", "courseTitle": "Electrical and Controls II", "creditHours": 0, "maximumEnrollment": 16, "enrollment": 0, "seatsAvailable": 16, "waitCapacity": 0, "waitCount": 0, "waitAvailable": 0, "crossList": null, "crossListCapacity": null, "crossListCount": null, "crossListAvailable": null, "creditHourHigh": 3, "creditHourLow": 0, "creditHourIndicator": "OR", "openSection": true, "linkIdentifier": "K2", "isSectionLinked": true, "subjectCourse": "ELCT304", "faculty": [], "meetingsFaculty": [{"category": "01", "class": "net.hedtech.banner.student.schedule.SectionSessionDecorator", "courseReferenceNumber": "21335", "faculty": [], "meetingTime": {"beginTime": "0800", "building": "KA", "buildingDescription": "Johnson-Cobbe Energy Centre", "campus": "MC", "campusDescription": "Main Campus", "category": "01", "class": "net.hedtech.banner.general.overall.MeetingTimeDecorator", "courseReferenceNumber": "21335", "creditHourSession": 0.0, "endDate": "11/22/2024", "endTime": "0950", "friday": false, "hoursWeek": 2.0, "meetingScheduleType": "B", "meetingType": "CLAS", "meetingTypeDescription": "Class", "monday": false, "room": "KA217", "saturday": false, "startDate": "10/21/2024", "sunday": false, "term": "202420", "thursday": false, "tuesday": true, "wednesday": false}, "term": "202420"}, {"category": "01", "class": "net.hedtech.banner.student.schedule.SectionSessionDecorator", "courseReferenceNumber": "21335", "faculty": [], "meetingTime": {"beginTime": "0800", "building": "KA", "buildingDescription": "Johnson-Cobbe Energy Centre", "campus": "MC", "campusDescription": "Main Campus", "category": "01", "class": "net.hedtech.banner.general.overall.MeetingTimeDecorator", "courseReferenceNumber": "21335", "creditHourSession": 0.0, "endDate": "11/22/2024", "endTime": "0950", "friday": false, "hoursWeek": 2.0, "meetingScheduleType": "B", "meetingType": "CLAS", "meetingTypeDescription": "Class", "monday": false, "room": "KA221", "saturday": false, "startDate": "10/21/2024", "sunday": false, "term": "202420", "thursday": false, "tuesday": true, "wednesday": false}, "term": "202420"}, {"category": "01", "class": "net.hedtech.banner.student.schedule.SectionSessionDecorator", "courseReferenceNumber": "21335", "faculty": [], "meetingTime": {"beginTime": "0800", "building": "KA", "buildingDescription": "Johnson-Cobbe Energy Centre", "campus": "MC", "campusDescription": "Main Campus", "category": "01", "class": "net.hedtech.banner.general.overall.MeetingTimeDecorator", "courseReferenceNumber": "21335", "creditHourSession": 0.0, "endDate": "10/18/2024", "endTime": "0950", "friday": false, "hoursWeek": 2.0, "meetingScheduleType": "B", "meetingType": "CLAS", "meetingTypeDescription": "Class", "monday": false, "room": "KA209", "saturday": false, "startDate": "09/03/2024", "sunday": false, "term": "202420", "thursday": false, "tuesday": true, "wednesday": false}, "term": "202420"}, {"category": "01", "class": "net.hedtech.banner.student.schedule.SectionSessionDecorator", "courseReferenceNumber": "21335", "faculty": [], "meetingTime": {"beginTime": "0800", "building": "KA", "buildingDescription": "Johnson-Cobbe Energy Centre", "campus": "MC", "campusDescription": "Main Campus", "category": "01", "class": "net.hedtech.banner.general.overall.MeetingTimeDecorator", "courseReferenceNumber": "21335", "creditHourSession": 0.0, "endDate": "12/06/2024", "endTime": "0950", "friday": false, "hoursWeek": 2.0, "meetingScheduleType": "B", "meetingType": "CLAS", "meetingTypeDescription": "Class", "monday": false, "room": "KA123", "saturday": false, "startDate": "11/25/2024", "sunday": false, "term": "202420", "thursday": false, "tuesday": true, "wednesday": false}, "term": "202420"}], "reservedSeatSummary": null, "sectionAttributes": [], "instructionalMethod": "IP", "instructionalMethodDescription": "In Person"}, {"id": 142205, "term": "202420", "termDesc": "Fall 2024", "courseReferenceNumber": "21336", "partOfTerm": "1", "courseNumber": "304", "subject": "ELCT", "subjectDescription": "Electrical", "sequenceNumber": "BBB", "campusDescription": "Main Campus", "scheduleTypeDescription": "Laboratory", "courseTitle": "Electrical and Controls II", "creditHours": 0, "maximumEnrollment": 16, "enrollment": 0, "seatsAvailable": 16, "waitCapacity": 0, "waitCount": 0, "waitAvailable": 0, "crossList": null, "crossListCapacity": null, "crossListCount": null, "crossListAvailable": null, "creditHourHigh": 3, "creditHourLow": 0, "creditHourIndicator": "OR", "openSection": true, "linkIdentifier": "K2", "isSectionLinked": true, "subjectCourse": "ELCT304", "faculty": [], "meetingsFaculty": [{"category": "01", "class": "net.hedtech.banner.student.schedule.SectionSessionDecorator", "courseReferenceNumber": "21336", "faculty": [], "meetingTime": {"beginTime": "1400", "building": "KA", "buildingDescription": "Johnson-Cobbe Energy Centre", "campus": "MC", "campusDescription": "Main Campus", "category": "01", "class": "net.hedtech.banner.general.overall.MeetingTimeDecorator", "courseReferenceNumber": "21336", "creditHourSession": 0.0, "endDate": "11/22/2024", "endTime": "1550", "friday": true, "hoursWeek": 2.0, "meetingScheduleType": "B", "meetingType": "CLAS", "meetingTypeDescription": "Class", "monday": false, "room": "KA217", "saturday": false, "startDate": "10/21/2024", "sunday": false, "term": "202420", "thursday": false, "tuesday": false, "wednesday": false}, "term": "202420"}, {"category": "01", "class": "net.hedtech.banner.student.schedule.SectionSessionDecorator", "courseReferenceNumber": "21336", "faculty": [], "meetingTime": {"beginTime": "1400", "building": "KA", "buildingDescription": "Johnson-Cobbe Energy Centre", "campus": "MC", "campusDescription": "Main Campus", "category": "01", "class": "net.hedtech.banner.general.overall.MeetingTimeDecorator", "courseReferenceNumber": "21336", "creditHourSession": 0.0, "endDate": "10/18/2024", "endTime": "1550", "friday": true, "hoursWeek": 2.0, "meetingScheduleType": "B", "meetingType": "CLAS", "meetingTypeDescription": "Class", "monday": false, "room": "KA209", "saturday": false, "startDate": "09/03/2024", "sunday": false, "term": "202420", "thursday": false, "tuesday": false, "wednesday": false}, "term": "202420"}, {"category": "01", "class": "net.hedtech.banner.student.schedule.SectionSessionDecorator", "courseReferenceNumber": "21336", "faculty": [], "meetingTime": {"beginTime": "1400", "building": "KA", "buildingDescription": "Johnson-Cobbe Energy Centre", "campus": "MC", "campusDescription": "Main Campus", "category": "01", "class": "net.hedtech.banner.general.overall.MeetingTimeDecorator", "courseReferenceNumber": "21336", "creditHourSession": 0.0, "endDate": "12/06/2024", "endTime": "1550", "friday": true, "hoursWeek": 2.0, "meetingScheduleType": "B", "meetingType": "CLAS", "meetingTypeDescription": "Class", "monday": false, "room": "KA123", "saturday": false, "startDate": "11/25/2024", "sunday": false, "term": "202420", "thursday": false, "tuesday": false, "wednesday": false}, "term": "202420"}], "reservedSeatSummary": null, "sectionAttributes": [], "instructionalMethod": "IP", "instructionalMethodDescription": "In Person"}, {"id": 141648, "term": "202420", "termDesc": "Fall 2024", "courseReferenceNumber": "21337", "partOfTerm": "1", "courseNumber": "304", "subject": "ELCT", "subjectDescription": "Electrical", "sequenceNumber": "C", "campusDescription": "Main Campus", "scheduleTypeDescription": "Lecture", "courseTitle": "Electrical and Controls II", "creditHours": 3, "maximumEnrollment": 32, "enrollment": 0, "seatsAvailable": 32, "waitCapacity": 0, "waitCount": 0, "waitAvailable": 0, "crossList": null, "crossListCapacity": null, "crossListCount": null, "crossListAvailable": null, "creditHourHigh": 3, "creditHourLow": 0, "creditHourIndicator": "OR", "openSection": true, "linkIdentifier": "A3", "isSectionLinked": true, "subjectCourse": "ELCT304", "faculty": [], "meetingsFaculty": [{"category": "01", "class": "net.hedtech.banner.student.schedule.SectionSessionDecorator", "courseReferenceNumber": "21337", "faculty": [], "meetingTime": {"beginTime": "1100", "building": "T", "buildingDescription": "Thomas Riley Building", "campus": "MC", "campusDescription": "Main Campus", "category": "01", "class": "net.hedtech.banner.general.overall.MeetingTimeDecorator", "courseReferenceNumber": "21337", "creditHourSession": 3.0, "endDate": "12/16/2024", "endTime": "1150", "friday": false, "hoursWeek": 1.0, "meetingScheduleType": "L", "meetingType": "CLAS", "meetingTypeDescription": "Class", "monday": false, "room": "TT225", "saturday": false, "startDate": "09/03/2024", "sunday": false, "term": "202420", "thursday": true, "tuesday": false, "wednesday": false}, "term": "202420"}, {"category": "01", "class": "net.hedtech.banner.student.schedule.SectionSessionDecorator", "courseReferenceNumber": "21337", "faculty": [], "meetingTime": {"beginTime": "1300", "building": "M", "buildingDescription": "Stan Grad Centre", "campus": "MC", "campusDescription": "Main Campus", "category": "01", "class": "net.hedtech.banner.general.overall.MeetingTimeDecorator", "courseReferenceNumber": "21337", "creditHourSession": 0.0, "endDate": "12/16/2024", "endTime": "1450", "friday": false, "hoursWeek": 2.0, "meetingScheduleType": "L", "meetingType": "CLAS", "meetingTypeDescription": "Class", "monday": true, "room": "MB323", "saturday": false, "startDate": "09/03/2024", "sunday": false, "term": "202420", "thursday": false, "tuesday": false, "wednesday": false}, "term": "202420"}], "reservedSeatSummary": null, "sectionAttributes": [], "instructionalMethod": "IP", "instructionalMethodDescription": "In Person"}, {"id": 142703, "term": "202420", "termDesc": "Fall 2024", "courseReferenceNumber": "21338", "partOfTerm": "1", "courseNumber": "304", "subject": "ELCT", "subjectDescription": "Electrical", "sequenceNumber": "CC", "campusDescription": "Main Campus", "scheduleTypeDescription": "Laboratory", "courseTitle": "Electrical and Controls II", "creditHours": 0, "maximumEnrollment": 16, "enrollment": 0, "seatsAvailable": 16, "waitCapacity": 0, "waitCount": 0, "waitAvailable": 0, "crossList": null, "crossListCapacity": null, "crossListCount": null, "crossListAvailable": null, "creditHourHigh": 3, "creditHourLow": 0, "creditHourIndicator": "OR", "openSection": true, "linkIdentifier": "K3", "isSectionLinked": true, "subjectCourse": "ELCT304", "faculty": [], "meetingsFaculty": [{"category": "01", "class": "net.hedtech.banner.student.schedule.SectionSessionDecorator", "courseReferenceNumber": "21338", "faculty": [], "meetingTime": {"beginTime": "1200", "building": "KA", "buildingDescription": "Johnson-Cobbe Energy Centre", "campus": "MC", "campusDescription": "Main Campus", "category": "01", "class": "net.hedtech.banner.general.overall.MeetingTimeDecorator", "courseReferenceNumber": "21338", "creditHourSession": 0.0, "endDate": "11/22/2024", "endTime": "1350", "friday": false, "hoursWeek": 2.0, "meetingScheduleType": "B", "meetingType": "CLAS", "meetingTypeDescription": "Class", "monday": false, "room": "KA217", "saturday": false, "startDate": "10/21/2024", "sunday": false, "term": "202420", "thursday": false, "tuesday": false, "wednesday": true}, "term": "202420"}, {"category": "01", "class": "net.hedtech.banner.student.schedule.SectionSessionDecorator", "courseReferenceNumber": "21338", "faculty": [], "meetingTime": {"beginTime": "1200", "building": "KA", "buildingDescription": "Johnson-Cobbe Energy Centre", "campus": "MC", "campusDescription": "Main Campus", "category": "01", "class": "net.hedtech.banner.general.overall.MeetingTimeDecorator", "courseReferenceNumber": "21338", "creditHourSession": 0.0, "endDate": "11/22/2024", "endTime": "1350", "friday": false, "hoursWeek": 2.0, "meetingScheduleType": "B", "meetingType": "CLAS", "meetingTypeDescription": "Class", "monday": false, "room": "KA221", "saturday": false, "startDate": "10/21/2024", "sunday": false, "term": "202420", "thursday": false, "tuesday": false, "wednesday": true}, "term": "202420"}, {"category": "01", "class": "net.hedtech.banner.student.schedule.SectionSessionDecorator", "courseReferenceNumber": "21338", "faculty": [], "meetingTime": {"beginTime": "1200", "building": "KA", "buildingDescription": "Johnson-Cobbe Energy Centre", "campus": "MC", "campusDescription": "Main Campus", "category": "01", "class": "net.hedtech.banner.general.overall.MeetingTimeDecorator", "courseReferenceNumber": "21338", "creditHourSession": 0.0, "endDate": "10/18/2024", "endTime": "1350", "friday": false, "hoursWeek": 2.0, "meetingScheduleType": "B", "meetingType": "CLAS", "meetingTypeDescription": "Class", "monday": false, "room": "KA208", "saturday": false, "startDate": "09/03/2024", "sunday": false, "term": "202420", "thursday": false, "tuesday": false, "wednesday": true}, "term": "202420"}, {"category": "01", "class": "net.hedtech.banner.student.schedule.SectionSessionDecorator", "courseReferenceNumber": "21338", "faculty": [], "meetingTime": {"beginTime": "1200", "building": "KA", "buildingDescription": "Johnson-Cobbe Energy Centre", "campus": "MC", "campusDescription": "Main Campus", "category": "01", "class": "net.hedtech.banner.general.overall.MeetingTimeDecorator", "courseReferenceNumber": "21338", "creditHourSession": 0.0, "endDate": "12/06/2024", "endTime": "1350", "friday": false, "hoursWeek": 2.0, "meetingScheduleType": "B", "meetingType": "CLAS", "meetingTypeDescription": "Class", "monday": false, "room": "KA123", "saturday": false, "startDate": "11/25/2024", "sunday": false, "term": "202420", "thursday": false, "tuesday": false, "wednesday": true}, "term": "202420"}], "reservedSeatSummary": null, "sectionAttributes": [], "instructionalMethod": "IP", "instructionalMethodDescription": "In Person"}, {"id": 142704, "term": "202420", "termDesc": "Fall 2024", "courseReferenceNumber": "21339", "partOfTerm": "1", "courseNumber": "304", "subject": "ELCT", "subjectDescription": "Electrical", "sequenceNumber": "CCC", "campusDescription": "Main Campus", "scheduleTypeDescription": "Laboratory", "courseTitle": "Electrical and Controls II", "creditHours": 0, "maximumEnrollment": 16, "enrollment": 0, "seatsAvailable": 16, "waitCapacity": 0, "waitCount": 0, "waitAvailable": 0, "crossList": null, "crossListCapacity": null, "crossListCount": null, "crossListAvailable": null, "creditHourHigh": 3, "creditHourLow": 0, "creditHourIndicator": "OR", "openSection": true, "linkIdentifier": "K3", "isSectionLinked": true, "subjectCourse": "ELCT304", "faculty": [], "meetingsFaculty": [{"category": "01", "class": "net.hedtech.banner.student.schedule.SectionSessionDecorator", "courseReferenceNumber": "21339", "faculty": [], "meetingTime": {"beginTime": "1100", "building": "KA", "buildingDescription": "Johnson-Cobbe Energy Centre", "campus": "MC", "campusDescription": "Main Campus", "category": "01", "class": "net.hedtech.banner.general.overall.MeetingTimeDecorator", "courseReferenceNumber": "21339", "creditHourSession": 0.0, "endDate": "11/22/2024", "endTime": "1250", "friday": true, "hoursWeek": 2.0, "meetingScheduleType": "B", "meetingType": "CLAS", "meetingTypeDescription": "Class", "monday": false, "room": "KA217", "saturday": false, "startDate": "10/21/2024", "sunday": false, "term": "202420", "thursday": false, "tuesday": false, "wednesday": false}, "term": "202420"}, {"category": "01", "class": "net.hedtech.banner.student.schedule.SectionSessionDecorator", "courseReferenceNumber": "21339", "faculty": [], "meetingTime": {"beginTime": "1100", "building": "KA", "buildingDescription": "Johnson-Cobbe Energy Centre", "campus": "MC", "campusDescription": "Main Campus", "category": "01", "class": "net.hedtech.banner.general.overall.MeetingTimeDecorator", "courseReferenceNumber": "21339", "creditHourSession": 0.0, "endDate": "11/22/2024", "endTime": "1250", "friday": true, "hoursWeek": 2.0, "meetingScheduleType": "B", "meetingType": "CLAS", "meetingTypeDescription": "Class", "monday": false, "room": "KA221", "saturday": false, "startDate": "10/21/2024", "sunday": false, "term": "202420", "thursday": false, "tuesday": false, "wednesday": false}, "term": "202420"}, {"category": "01", "class": "net.hedtech.banner.student.schedule.SectionSessionDecorator", "courseReferenceNumber": "21339", "faculty": [], "meetingTime": {"beginTime": "1100", "building": "KA", "buildingDescription": "Johnson-Cobbe Energy Centre", "campus": "MC", "campusDescription": "Main Campus", "category": "01", "class": "net.hedtech.banner.general.overall.MeetingTimeDecorator", "courseReferenceNumber": "21339", "creditHourSession": 0.0, "endDate": "10/18/2024", "endTime": "1250", "friday": true, "hoursWeek": 2.0, "meetingScheduleType": "B", "meetingType": "CLAS", "meetingTypeDescription": "Class", "monday": false, "room": "KA209", "saturday": false, "startDate": "09/03/2024", "sunday": false, "term": "202420", "thursday": false, "tuesday": false, "wednesday": false}, "term": "202420"}, {"category": "01", "class": "net.hedtech.banner.student.schedule.SectionSessionDecorator", "courseReferenceNumber": "21339", "faculty": [], "meetingTime": {"beginTime": "1100", "building": "KA", "buildingDescription": "Johnson-Cobbe Energy Centre", "campus": "MC", "campusDescription": "Main Campus", "category": "01", "class": "net.hedtech.banner.general.overall.MeetingTimeDecorator", "courseReferenceNumber": "21339", "creditHourSession": 0.0, "endDate": "12/06/2024", "endTime": "1250", "friday": true, "hoursWeek": 2.0, "meetingScheduleType": "B", "meetingType": "CLAS", "meetingTypeDescription": "Class", "monday": false, "room": "KA123", "saturday": false, "startDate": "11/25/2024", "sunday": false, "term": "202420", "thursday": false, "tuesday": false, "wednesday": false}, "term": "202420"}], "reservedSeatSummary": null, "sectionAttributes": [], "instructionalMethod": "IP", "instructionalMethodDescription": "In Person"}, {"id": 142811, "term": "202420", "termDesc": "Fall 2024", "courseReferenceNumber": "21340", "partOfTerm": "1", "courseNumber": "304", "subject": "ELCT", "subjectDescription": "Electrical", "sequenceNumber": "D", "campusDescription": "Main Campus", "scheduleTypeDescription": "Lecture", "courseTitle": "Electrical and Controls II", "creditHours": 3, "maximumEnrollment": 32, "enrollment": 0, "seatsAvailable": 32, "waitCapacity": 0, "waitCount": 0, "waitAvailable": 0, "crossList": null, "crossListCapacity": null, "crossListCount": null, "crossListAvailable": null, "creditHourHigh": 3, "creditHourLow": 0, "creditHourIndicator": "OR", "openSection": true, "linkIdentifier": "A4", "isSectionLinked": true, "subjectCourse": "ELCT304", "faculty": [], "meetingsFaculty": [{"category": "01", "class": "net.hedtech.banner.student.schedule.SectionSessionDecorator", "courseReferenceNumber": "21340", "faculty": [], "meetingTime": {"beginTime": "1200", "building": "T", "buildingDescription": "Thomas Riley Building", "campus": "MC", "campusDescription": "Main Campus", "category": "01", "class": "net.hedtech.banner.general.overall.MeetingTimeDecorator", "courseReferenceNumber": "21340", "creditHourSession": 0.0, "endDate": "12/16/2024", "endTime": "1350", "friday": false, "hoursWeek": 2.0, "meetingScheduleType": "L", "meetingType": "CLAS", "meetingTypeDescription": "Class", "monday": false, "room": "TT239", "saturday": false, "startDate": "09/03/2024", "sunday": false, "term": "202420", "thursday": true, "tuesday": false, "wednesday": false}, "term": "202420"}, {"category": "01", "class": "net.hedtech.banner.student.schedule.SectionSessionDecorator", "courseReferenceNumber": "21340", "faculty": [], "meetingTime": {"beginTime": "1600", "building": "T", "buildingDescription": "Thomas Riley Building", "campus": "MC", "campusDescription": "Main Campus", "category": "01", "class": "net.hedtech.banner.general.overall.MeetingTimeDecorator", "courseReferenceNumber": "21340", "creditHourSession": 3.0, "endDate": "12/16/2024", "endTime": "1650", "friday": false, "hoursWeek": 1.0, "meetingScheduleType": "L", "meetingType": "CLAS", "meetingTypeDescription": "Class", "monday": false, "room": "TT225", "saturday": false, "startDate": "09/03/2024", "sunday": false, "term": "202420", "thursday": false, "tuesday": true, "wednesday": false}, "term": "202420"}], "reservedSeatSummary": null, "sectionAttributes": [], "instructionalMethod": "IP", "instructionalMethodDescription": "In Person"}, {"id": 142812, "term": "202420", "termDesc": "Fall 2024", "courseReferenceNumber": "21341", "partOfTerm": "1", "courseNumber": "304", "subject": "ELCT", "subjectDescription": "Electrical", "sequenceNumber": "DD", "campusDescription": "Main Campus", "scheduleTypeDescription": "Laboratory", "courseTitle": "Electrical and Controls II", "creditHours": 0, "maximumEnrollment": 16, "enrollment": 0, "seatsAvailable": 16, "waitCapacity": 0, "waitCount": 0, "waitAvailable": 0, "crossList": null, "crossListCapacity": null, "crossListCount": null, "crossListAvailable": null, "creditHourHigh": 3, "creditHourLow": 0, "creditHourIndicator": "OR", "openSection": true, "linkIdentifier": "K4", "isSectionLinked": true, "subjectCourse": "ELCT304", "faculty": [], "meetingsFaculty": [{"category": "01", "class": "net.hedtech.banner.student.schedule.SectionSessionDecorator", "courseReferenceNumber": "21341", "faculty": [], "meetingTime": {"beginTime": "1000", "building": "KA", "buildingDescription": "Johnson-Cobbe Energy Centre", "campus": "MC", "campusDescription": "Main Campus", "category": "01", "class": "net.hedtech.banner.general.overall.MeetingTimeDecorator", "courseReferenceNumber": "21341", "creditHourSession": 0.0, "endDate": "11/22/2024", "endTime": "1150", "friday": false, "hoursWeek": 2.0, "meetingScheduleType": "B", "meetingType": "CLAS", "meetingTypeDescription": "Class", "monday": true, "room": "KA225", "saturday": false, "startDate": "10/21/2024", "sunday": false, "term": "202420", "thursday": false, "tuesday": false, "wednesday": false}, "term": "202420"}, {"category": "01", "class": "net.hedtech.banner.student.schedule.SectionSessionDecorator", "courseReferenceNumber": "21341", "faculty": [], "meetingTime": {"beginTime": "1000", "building": "KA", "buildingDescription": "Johnson-Cobbe Energy Centre", "campus": "MC", "campusDescription": "Main Campus", "category": "01", "class": "net.hedtech.banner.general.overall.MeetingTimeDecorator", "courseReferenceNumber": "21341", "creditHourSession": 0.0, "endDate": "11/22/2024", "endTime": "1150", "friday": false, "hoursWeek": 2.0, "meetingScheduleType": "B", "meetingType": "CLAS", "meetingTypeDescription": "Class", "monday": true, "room": "KA123", "saturday": false, "startDate": "10/21/2024", "sunday": false, "term": "202420", "thursday": false, "tuesday": false, "wednesday": false}, "term": "202420"}, {"category": "01", "class": "net.hedtech.banner.student.schedule.SectionSessionDecorator", "courseReferenceNumber": "21341", "faculty": [], "meetingTime": {"beginTime": "1500", "building": "KA", "buildingDescription": "Johnson-Cobbe Energy Centre", "campus": "MC", "campusDescription": "Main Campus", "category": "01", "class": "net.hedtech.banner.general.overall.MeetingTimeDecorator", "courseReferenceNumber": "21341", "creditHourSession": 0.0, "endDate": "10/18/2024", "endTime": "1650", "friday": false, "hoursWeek": 2.0, "meetingScheduleType": "B", "meetingType": "CLAS", "meetingTypeDescription": "Class", "monday": false, "room": "KA209", "saturday": false, "startDate": "09/03/2024", "sunday": false, "term": "202420", "thursday": false, "tuesday": false, "wednesday": true}, "term": "202420"}, {"category": "01", "class": "net.hedtech.banner.student.schedule.SectionSessionDecorator", "courseReferenceNumber": "21341", "faculty": [], "meetingTime": {"beginTime": "1500", "building": "KA", "buildingDescription": "Johnson-Cobbe Energy Centre", "campus": "MC", "campusDescription": "Main Campus", "category": "01", "class": "net.hedtech.banner.general.overall.MeetingTimeDecorator", "courseReferenceNumber": "21341", "creditHourSession": 0.0, "endDate": "12/06/2024", "endTime": "1650", "friday": false, "hoursWeek": 2.0, "meetingScheduleType": "B", "meetingType": "CLAS", "meetingTypeDescription": "Class", "monday": false, "room": "KA123", "saturday": false, "startDate": "11/25/2024", "sunday": false, "term": "202420", "thursday": false, "tuesday": false, "wednesday": true}, "term": "202420"}], "reservedSeatSummary": null, "sectionAttributes": [], "instructionalMethod": "IP", "instructionalMethodDescription": "In Person"}, {"id": 142810, "term": "202420", "termDesc": "Fall 2024", "courseReferenceNumber": "21342", "partOfTerm": "1", "courseNumber": "304", "subject": "ELCT", "subjectDescription": "Electrical", "sequenceNumber": "DDD", "campusDescription": "Main Campus", "scheduleTypeDescription": "Laboratory", "courseTitle": "Electrical and Controls II", "creditHours": 0, "maximumEnrollment": 16, "enrollment": 0, "seatsAvailable": 16, "waitCapacity": 0, "waitCount": 0, "waitAvailable": 0, "crossList": null, "crossListCapacity": null, "crossListCount": null, "crossListAvailable": null, "creditHourHigh": 3, "creditHourLow": 0, "creditHourIndicator": "OR", "openSection": true, "linkIdentifier": "K4", "isSectionLinked": true, "subjectCourse": "ELCT304", "faculty": [], "meetingsFaculty": [{"category": "01", "class": "net.hedtech.banner.student.schedule.SectionSessionDecorator", "courseReferenceNumber": "21342", "faculty": [], "meetingTime": {"beginTime": "0800", "building": "KA", "buildingDescription": "Johnson-Cobbe Energy Centre", "campus": "MC", "campusDescription": "Main Campus", "category": "01", "class": "net.hedtech.banner.general.overall.MeetingTimeDecorator", "courseReferenceNumber": "21342", "creditHourSession": 0.0, "endDate": "10/18/2024", "endTime": "0950", "friday": false, "hoursWeek": 2.0, "meetingScheduleType": "B", "meetingType": "CLAS", "meetingTypeDescription": "Class", "monday": false, "room": "KA215", "saturday": false, "startDate": "09/03/2024", "sunday": false, "term": "202420", "thursday": true, "tuesday": false, "wednesday": false}, "term": "202420"}, {"category": "01", "class": "net.hedtech.banner.student.schedule.SectionSessionDecorator", "courseReferenceNumber": "21342", "faculty": [], "meetingTime": {"beginTime": "0800", "building": "KA", "buildingDescription": "Johnson-Cobbe Energy Centre", "campus": "MC", "campusDescription": "Main Campus", "category": "01", "class": "net.hedtech.banner.general.overall.MeetingTimeDecorator", "courseReferenceNumber": "21342", "creditHourSession": 0.0, "endDate": "11/22/2024", "endTime": "0950", "friday": false, "hoursWeek": 2.0, "meetingScheduleType": "B", "meetingType": "CLAS", "meetingTypeDescription": "Class", "monday": false, "room": "KA221", "saturday": false, "startDate": "10/21/2024", "sunday": false, "term": "202420", "thursday": true, "tuesday": false, "wednesday": false}, "term": "202420"}, {"category": "01", "class": "net.hedtech.banner.student.schedule.SectionSessionDecorator", "courseReferenceNumber": "21342", "faculty": [], "meetingTime": {"beginTime": "0800", "building": "KA", "buildingDescription": "Johnson-Cobbe Energy Centre", "campus": "MC", "campusDescription": "Main Campus", "category": "01", "class": "net.hedtech.banner.general.overall.MeetingTimeDecorator", "courseReferenceNumber": "21342", "creditHourSession": 0.0, "endDate": "11/22/2024", "endTime": "0950", "friday": false, "hoursWeek": 2.0, "meetingScheduleType": "B", "meetingType": "CLAS", "meetingTypeDescription": "Class", "monday": false, "room": "KA217", "saturday": false, "startDate": "10/21/2024", "sunday": false, "term": "202420", "thursday": true, "tuesday": false, "wednesday": false}, "term": "202420"}, {"category": "01", "class": "net.hedtech.banner.student.schedule.SectionSessionDecorator", "courseReferenceNumber": "21342", "faculty": [], "meetingTime": {"beginTime": "1000", "building": "KA", "buildingDescription": "Johnson-Cobbe Energy Centre", "campus": "MC", "campusDescription": "Main Campus", "category": "01", "class": "net.hedtech.banner.general.overall.MeetingTimeDecorator", "courseReferenceNumber": "21342", "creditHourSession": 0.0, "endDate": "12/06/2024", "endTime": "1150", "friday": false, "hoursWeek": 2.0, "meetingScheduleType": "B", "meetingType": "CLAS", "meetingTypeDescription": "Class", "monday": false, "room": "KA123", "saturday": false, "startDate": "11/25/2024", "sunday": false, "term": "202420", "thursday": false, "tuesday": true, "wednesday": false}, "term": "202420"}], "reservedSeatSummary": null, "sectionAttributes": [], "instructionalMethod": "IP", "instructionalMethodDescription": "In Person"}]}