{"code": "FTNS", "description": "Fitness/Safety/Wellness", "entries": 6, "data": [{"id": 139361, "term": "202420", "termDesc": "Fall 2024", "courseReferenceNumber": "21548", "partOfTerm": "1", "courseNumber": "205", "subject": "FTNS", "subjectDescription": "Fitness/Safety/Wellness", "sequenceNumber": "FWA", "campusDescription": "Main Campus", "scheduleTypeDescription": "Laboratory", "courseTitle": "Foundations in Strength and Conditioning", "creditHours": 0, "maximumEnrollment": 18, "enrollment": 0, "seatsAvailable": 18, "waitCapacity": 0, "waitCount": 0, "waitAvailable": 0, "crossList": null, "crossListCapacity": null, "crossListCount": null, "crossListAvailable": null, "creditHourHigh": 3, "creditHourLow": 0, "creditHourIndicator": "TO", "openSection": true, "linkIdentifier": "K1", "isSectionLinked": true, "subjectCourse": "FTNS205", "faculty": [], "meetingsFaculty": [{"category": "01", "class": "net.hedtech.banner.student.schedule.SectionSessionDecorator", "courseReferenceNumber": "21548", "faculty": [], "meetingTime": {"beginTime": "0900", "building": "N", "buildingDescription": "Senator Burns Building", "campus": "MC", "campusDescription": "Main Campus", "category": "01", "class": "net.hedtech.banner.general.overall.MeetingTimeDecorator", "courseReferenceNumber": "21548", "creditHourSession": 0.0, "endDate": "12/16/2024", "endTime": "1050", "friday": false, "hoursWeek": 2.0, "meetingScheduleType": "B", "meetingType": "CLAS", "meetingTypeDescription": "Class", "monday": false, "room": "NR009", "saturday": false, "startDate": "09/03/2024", "sunday": false, "term": "202420", "thursday": false, "tuesday": false, "wednesday": true}, "term": "202420"}], "reservedSeatSummary": null, "sectionAttributes": [], "instructionalMethod": "IP", "instructionalMethodDescription": "In Person"}, {"id": 142853, "term": "202420", "termDesc": "Fall 2024", "courseReferenceNumber": "21549", "partOfTerm": "1", "courseNumber": "205", "subject": "FTNS", "subjectDescription": "Fitness/Safety/Wellness", "sequenceNumber": "FWB", "campusDescription": "Main Campus", "scheduleTypeDescription": "Laboratory", "courseTitle": "Foundations in Strength and Conditioning", "creditHours": 0, "maximumEnrollment": 18, "enrollment": 0, "seatsAvailable": 18, "waitCapacity": 0, "waitCount": 0, "waitAvailable": 0, "crossList": null, "crossListCapacity": null, "crossListCount": null, "crossListAvailable": null, "creditHourHigh": 3, "creditHourLow": 0, "creditHourIndicator": "TO", "openSection": true, "linkIdentifier": "K1", "isSectionLinked": true, "subjectCourse": "FTNS205", "faculty": [], "meetingsFaculty": [{"category": "01", "class": "net.hedtech.banner.student.schedule.SectionSessionDecorator", "courseReferenceNumber": "21549", "faculty": [], "meetingTime": {"beginTime": "1200", "building": "N", "buildingDescription": "Senator Burns Building", "campus": "MC", "campusDescription": "Main Campus", "category": "01", "class": "net.hedtech.banner.general.overall.MeetingTimeDecorator", "courseReferenceNumber": "21549", "creditHourSession": 0.0, "endDate": "12/16/2024", "endTime": "1350", "friday": false, "hoursWeek": 2.0, "meetingScheduleType": "B", "meetingType": "CLAS", "meetingTypeDescription": "Class", "monday": false, "room": "NR009", "saturday": false, "startDate": "09/03/2024", "sunday": false, "term": "202420", "thursday": false, "tuesday": false, "wednesday": true}, "term": "202420"}], "reservedSeatSummary": null, "sectionAttributes": [], "instructionalMethod": "IP", "instructionalMethodDescription": "In Person"}, {"id": 142753, "term": "202420", "termDesc": "Fall 2024", "courseReferenceNumber": "21550", "partOfTerm": "1", "courseNumber": "205", "subject": "FTNS", "subjectDescription": "Fitness/Safety/Wellness", "sequenceNumber": "FWM", "campusDescription": "Main Campus", "scheduleTypeDescription": "Lecture", "courseTitle": "Foundations in Strength and Conditioning", "creditHours": 3, "maximumEnrollment": 36, "enrollment": 0, "seatsAvailable": 36, "waitCapacity": 0, "waitCount": 0, "waitAvailable": 0, "crossList": null, "crossListCapacity": null, "crossListCount": null, "crossListAvailable": null, "creditHourHigh": 3, "creditHourLow": 0, "creditHourIndicator": "TO", "openSection": true, "linkIdentifier": "A1", "isSectionLinked": true, "subjectCourse": "FTNS205", "faculty": [], "meetingsFaculty": [{"category": "01", "class": "net.hedtech.banner.student.schedule.SectionSessionDecorator", "courseReferenceNumber": "21550", "faculty": [], "meetingTime": {"beginTime": "0800", "building": "N", "buildingDescription": "Senator Burns Building", "campus": "MC", "campusDescription": "Main Campus", "category": "01", "class": "net.hedtech.banner.general.overall.MeetingTimeDecorator", "courseReferenceNumber": "21550", "creditHourSession": 3.0, "endDate": "12/16/2024", "endTime": "0950", "friday": false, "hoursWeek": 2.0, "meetingScheduleType": "L", "meetingType": "CLAS", "meetingTypeDescription": "Class", "monday": true, "room": "NN904", "saturday": false, "startDate": "09/03/2024", "sunday": false, "term": "202420", "thursday": false, "tuesday": false, "wednesday": false}, "term": "202420"}], "reservedSeatSummary": null, "sectionAttributes": [], "instructionalMethod": "IP", "instructionalMethodDescription": "In Person"}, {"id": 141958, "term": "202420", "termDesc": "Fall 2024", "courseReferenceNumber": "21551", "partOfTerm": "1", "courseNumber": "300", "subject": "FTNS", "subjectDescription": "Fitness/Safety/Wellness", "sequenceNumber": "FWA", "campusDescription": "Main Campus", "scheduleTypeDescription": "Laboratory", "courseTitle": "Functional Movement and Mobility", "creditHours": 0, "maximumEnrollment": 10, "enrollment": 0, "seatsAvailable": 10, "waitCapacity": 0, "waitCount": 0, "waitAvailable": 0, "crossList": null, "crossListCapacity": null, "crossListCount": null, "crossListAvailable": null, "creditHourHigh": 3, "creditHourLow": 0, "creditHourIndicator": "OR", "openSection": true, "linkIdentifier": "K1", "isSectionLinked": true, "subjectCourse": "FTNS300", "faculty": [], "meetingsFaculty": [{"category": "01", "class": "net.hedtech.banner.student.schedule.SectionSessionDecorator", "courseReferenceNumber": "21551", "faculty": [], "meetingTime": {"beginTime": "0900", "building": "N", "buildingDescription": "Senator Burns Building", "campus": "MC", "campusDescription": "Main Campus", "category": "01", "class": "net.hedtech.banner.general.overall.MeetingTimeDecorator", "courseReferenceNumber": "21551", "creditHourSession": 0.0, "endDate": "12/16/2024", "endTime": "1050", "friday": false, "hoursWeek": 2.0, "meetingScheduleType": "B", "meetingType": "CLAS", "meetingTypeDescription": "Class", "monday": false, "room": "NR009", "saturday": false, "startDate": "09/03/2024", "sunday": false, "term": "202420", "thursday": true, "tuesday": false, "wednesday": false}, "term": "202420"}], "reservedSeatSummary": null, "sectionAttributes": [], "instructionalMethod": "IP", "instructionalMethodDescription": "In Person"}, {"id": 141102, "term": "202420", "termDesc": "Fall 2024", "courseReferenceNumber": "21552", "partOfTerm": "1", "courseNumber": "300", "subject": "FTNS", "subjectDescription": "Fitness/Safety/Wellness", "sequenceNumber": "FWB", "campusDescription": "Main Campus", "scheduleTypeDescription": "Laboratory", "courseTitle": "Functional Movement and Mobility", "creditHours": 0, "maximumEnrollment": 10, "enrollment": 0, "seatsAvailable": 10, "waitCapacity": 0, "waitCount": 0, "waitAvailable": 0, "crossList": null, "crossListCapacity": null, "crossListCount": null, "crossListAvailable": null, "creditHourHigh": 3, "creditHourLow": 0, "creditHourIndicator": "OR", "openSection": true, "linkIdentifier": "K1", "isSectionLinked": true, "subjectCourse": "FTNS300", "faculty": [], "meetingsFaculty": [{"category": "01", "class": "net.hedtech.banner.student.schedule.SectionSessionDecorator", "courseReferenceNumber": "21552", "faculty": [], "meetingTime": {"beginTime": "1200", "building": "N", "buildingDescription": "Senator Burns Building", "campus": "MC", "campusDescription": "Main Campus", "category": "01", "class": "net.hedtech.banner.general.overall.MeetingTimeDecorator", "courseReferenceNumber": "21552", "creditHourSession": 0.0, "endDate": "12/16/2024", "endTime": "1350", "friday": false, "hoursWeek": 2.0, "meetingScheduleType": "B", "meetingType": "CLAS", "meetingTypeDescription": "Class", "monday": false, "room": "NR009", "saturday": false, "startDate": "09/03/2024", "sunday": false, "term": "202420", "thursday": true, "tuesday": false, "wednesday": false}, "term": "202420"}], "reservedSeatSummary": null, "sectionAttributes": [], "instructionalMethod": "IP", "instructionalMethodDescription": "In Person"}, {"id": 139332, "term": "202420", "termDesc": "Fall 2024", "courseReferenceNumber": "21553", "partOfTerm": "1", "courseNumber": "300", "subject": "FTNS", "subjectDescription": "Fitness/Safety/Wellness", "sequenceNumber": "FWM", "campusDescription": "Main Campus", "scheduleTypeDescription": "Lecture", "courseTitle": "Functional Movement and Mobility", "creditHours": 3, "maximumEnrollment": 20, "enrollment": 0, "seatsAvailable": 20, "waitCapacity": 0, "waitCount": 0, "waitAvailable": 0, "crossList": null, "crossListCapacity": null, "crossListCount": null, "crossListAvailable": null, "creditHourHigh": 3, "creditHourLow": 0, "creditHourIndicator": "OR", "openSection": true, "linkIdentifier": "A1", "isSectionLinked": true, "subjectCourse": "FTNS300", "faculty": [], "meetingsFaculty": [{"category": "01", "class": "net.hedtech.banner.student.schedule.SectionSessionDecorator", "courseReferenceNumber": "21553", "faculty": [], "meetingTime": {"beginTime": "1300", "building": "N", "buildingDescription": "Senator Burns Building", "campus": "MC", "campusDescription": "Main Campus", "category": "01", "class": "net.hedtech.banner.general.overall.MeetingTimeDecorator", "courseReferenceNumber": "21553", "creditHourSession": 3.0, "endDate": "12/16/2024", "endTime": "1350", "friday": false, "hoursWeek": 1.0, "meetingScheduleType": "L", "meetingType": "CLAS", "meetingTypeDescription": "Class", "monday": false, "room": "NH214", "saturday": false, "startDate": "09/03/2024", "sunday": false, "term": "202420", "thursday": false, "tuesday": true, "wednesday": false}, "term": "202420"}], "reservedSeatSummary": null, "sectionAttributes": [], "instructionalMethod": "IP", "instructionalMethodDescription": "In Person"}]}