{"code": "GEOL", "description": "Geology", "entries": 9, "data": [{"id": 139714, "term": "202420", "termDesc": "Fall 2024", "courseReferenceNumber": "21615", "partOfTerm": "1", "courseNumber": "246", "subject": "GEOL", "subjectDescription": "Geology", "sequenceNumber": "A", "campusDescription": "Main Campus", "scheduleTypeDescription": "Lecture", "courseTitle": "Physical Geology", "creditHours": 3, "maximumEnrollment": 32, "enrollment": 0, "seatsAvailable": 32, "waitCapacity": 0, "waitCount": 0, "waitAvailable": 0, "crossList": null, "crossListCapacity": null, "crossListCount": null, "crossListAvailable": null, "creditHourHigh": 3, "creditHourLow": 0, "creditHourIndicator": "OR", "openSection": true, "linkIdentifier": "A1", "isSectionLinked": true, "subjectCourse": "GEOL246", "faculty": [], "meetingsFaculty": [{"category": "01", "class": "net.hedtech.banner.student.schedule.SectionSessionDecorator", "courseReferenceNumber": "21615", "faculty": [], "meetingTime": {"beginTime": "0800", "building": "T", "buildingDescription": "Thomas Riley Building", "campus": "MC", "campusDescription": "Main Campus", "category": "01", "class": "net.hedtech.banner.general.overall.MeetingTimeDecorator", "courseReferenceNumber": "21615", "creditHourSession": 0.0, "endDate": "12/16/2024", "endTime": "0950", "friday": true, "hoursWeek": 2.0, "meetingScheduleType": "L", "meetingType": "CLAS", "meetingTypeDescription": "Class", "monday": false, "room": "TT233", "saturday": false, "startDate": "09/03/2024", "sunday": false, "term": "202420", "thursday": false, "tuesday": false, "wednesday": false}, "term": "202420"}, {"category": "01", "class": "net.hedtech.banner.student.schedule.SectionSessionDecorator", "courseReferenceNumber": "21615", "faculty": [], "meetingTime": {"beginTime": "1200", "building": "KA", "buildingDescription": "Johnson-Cobbe Energy Centre", "campus": "MC", "campusDescription": "Main Campus", "category": "01", "class": "net.hedtech.banner.general.overall.MeetingTimeDecorator", "courseReferenceNumber": "21615", "creditHourSession": 3.0, "endDate": "12/16/2024", "endTime": "1250", "friday": false, "hoursWeek": 1.0, "meetingScheduleType": "L", "meetingType": "CLAS", "meetingTypeDescription": "Class", "monday": false, "room": "KA308", "saturday": false, "startDate": "09/03/2024", "sunday": false, "term": "202420", "thursday": false, "tuesday": false, "wednesday": true}, "term": "202420"}], "reservedSeatSummary": null, "sectionAttributes": [], "instructionalMethod": "IP", "instructionalMethodDescription": "In Person"}, {"id": 139715, "term": "202420", "termDesc": "Fall 2024", "courseReferenceNumber": "21616", "partOfTerm": "1", "courseNumber": "246", "subject": "GEOL", "subjectDescription": "Geology", "sequenceNumber": "AA", "campusDescription": "Main Campus", "scheduleTypeDescription": "Laboratory", "courseTitle": "Physical Geology", "creditHours": 0, "maximumEnrollment": 16, "enrollment": 0, "seatsAvailable": 16, "waitCapacity": 0, "waitCount": 0, "waitAvailable": 0, "crossList": null, "crossListCapacity": null, "crossListCount": null, "crossListAvailable": null, "creditHourHigh": 3, "creditHourLow": 0, "creditHourIndicator": "OR", "openSection": true, "linkIdentifier": "K1", "isSectionLinked": true, "subjectCourse": "GEOL246", "faculty": [], "meetingsFaculty": [{"category": "01", "class": "net.hedtech.banner.student.schedule.SectionSessionDecorator", "courseReferenceNumber": "21616", "faculty": [], "meetingTime": {"beginTime": "0900", "building": "KA", "buildingDescription": "Johnson-Cobbe Energy Centre", "campus": "MC", "campusDescription": "Main Campus", "category": "01", "class": "net.hedtech.banner.general.overall.MeetingTimeDecorator", "courseReferenceNumber": "21616", "creditHourSession": 0.0, "endDate": "12/16/2024", "endTime": "1050", "friday": false, "hoursWeek": 2.0, "meetingScheduleType": "B", "meetingType": "CLAS", "meetingTypeDescription": "Class", "monday": false, "room": "KA328", "saturday": false, "startDate": "09/03/2024", "sunday": false, "term": "202420", "thursday": true, "tuesday": false, "wednesday": false}, "term": "202420"}], "reservedSeatSummary": null, "sectionAttributes": [], "instructionalMethod": "IP", "instructionalMethodDescription": "In Person"}, {"id": 139716, "term": "202420", "termDesc": "Fall 2024", "courseReferenceNumber": "21617", "partOfTerm": "1", "courseNumber": "246", "subject": "GEOL", "subjectDescription": "Geology", "sequenceNumber": "AAA", "campusDescription": "Main Campus", "scheduleTypeDescription": "Laboratory", "courseTitle": "Physical Geology", "creditHours": 0, "maximumEnrollment": 16, "enrollment": 0, "seatsAvailable": 16, "waitCapacity": 0, "waitCount": 0, "waitAvailable": 0, "crossList": null, "crossListCapacity": null, "crossListCount": null, "crossListAvailable": null, "creditHourHigh": 3, "creditHourLow": 0, "creditHourIndicator": "OR", "openSection": true, "linkIdentifier": "K1", "isSectionLinked": true, "subjectCourse": "GEOL246", "faculty": [], "meetingsFaculty": [{"category": "01", "class": "net.hedtech.banner.student.schedule.SectionSessionDecorator", "courseReferenceNumber": "21617", "faculty": [], "meetingTime": {"beginTime": "1100", "building": "KA", "buildingDescription": "Johnson-Cobbe Energy Centre", "campus": "MC", "campusDescription": "Main Campus", "category": "01", "class": "net.hedtech.banner.general.overall.MeetingTimeDecorator", "courseReferenceNumber": "21617", "creditHourSession": 0.0, "endDate": "12/16/2024", "endTime": "1250", "friday": false, "hoursWeek": 2.0, "meetingScheduleType": "B", "meetingType": "CLAS", "meetingTypeDescription": "Class", "monday": false, "room": "KA328", "saturday": false, "startDate": "09/03/2024", "sunday": false, "term": "202420", "thursday": true, "tuesday": false, "wednesday": false}, "term": "202420"}], "reservedSeatSummary": null, "sectionAttributes": [], "instructionalMethod": "IP", "instructionalMethodDescription": "In Person"}, {"id": 142491, "term": "202420", "termDesc": "Fall 2024", "courseReferenceNumber": "21618", "partOfTerm": "1", "courseNumber": "246", "subject": "GEOL", "subjectDescription": "Geology", "sequenceNumber": "B", "campusDescription": "Main Campus", "scheduleTypeDescription": "Lecture", "courseTitle": "Physical Geology", "creditHours": 3, "maximumEnrollment": 32, "enrollment": 0, "seatsAvailable": 32, "waitCapacity": 0, "waitCount": 0, "waitAvailable": 0, "crossList": null, "crossListCapacity": null, "crossListCount": null, "crossListAvailable": null, "creditHourHigh": 3, "creditHourLow": 0, "creditHourIndicator": "OR", "openSection": true, "linkIdentifier": "A2", "isSectionLinked": true, "subjectCourse": "GEOL246", "faculty": [], "meetingsFaculty": [{"category": "01", "class": "net.hedtech.banner.student.schedule.SectionSessionDecorator", "courseReferenceNumber": "21618", "faculty": [], "meetingTime": {"beginTime": "1300", "building": "KA", "buildingDescription": "Johnson-Cobbe Energy Centre", "campus": "MC", "campusDescription": "Main Campus", "category": "01", "class": "net.hedtech.banner.general.overall.MeetingTimeDecorator", "courseReferenceNumber": "21618", "creditHourSession": 3.0, "endDate": "12/16/2024", "endTime": "1550", "friday": false, "hoursWeek": 3.0, "meetingScheduleType": "L", "meetingType": "CLAS", "meetingTypeDescription": "Class", "monday": true, "room": "KA308", "saturday": false, "startDate": "09/03/2024", "sunday": false, "term": "202420", "thursday": false, "tuesday": false, "wednesday": false}, "term": "202420"}], "reservedSeatSummary": null, "sectionAttributes": [], "instructionalMethod": "IP", "instructionalMethodDescription": "In Person"}, {"id": 142492, "term": "202420", "termDesc": "Fall 2024", "courseReferenceNumber": "21619", "partOfTerm": "1", "courseNumber": "246", "subject": "GEOL", "subjectDescription": "Geology", "sequenceNumber": "BB", "campusDescription": "Main Campus", "scheduleTypeDescription": "Laboratory", "courseTitle": "Physical Geology", "creditHours": 0, "maximumEnrollment": 16, "enrollment": 0, "seatsAvailable": 16, "waitCapacity": 0, "waitCount": 0, "waitAvailable": 0, "crossList": null, "crossListCapacity": null, "crossListCount": null, "crossListAvailable": null, "creditHourHigh": 3, "creditHourLow": 0, "creditHourIndicator": "OR", "openSection": true, "linkIdentifier": "K2", "isSectionLinked": true, "subjectCourse": "GEOL246", "faculty": [], "meetingsFaculty": [{"category": "01", "class": "net.hedtech.banner.student.schedule.SectionSessionDecorator", "courseReferenceNumber": "21619", "faculty": [], "meetingTime": {"beginTime": "1100", "building": "KA", "buildingDescription": "Johnson-Cobbe Energy Centre", "campus": "MC", "campusDescription": "Main Campus", "category": "01", "class": "net.hedtech.banner.general.overall.MeetingTimeDecorator", "courseReferenceNumber": "21619", "creditHourSession": 0.0, "endDate": "12/16/2024", "endTime": "1250", "friday": false, "hoursWeek": 2.0, "meetingScheduleType": "B", "meetingType": "CLAS", "meetingTypeDescription": "Class", "monday": false, "room": "KA328", "saturday": false, "startDate": "09/03/2024", "sunday": false, "term": "202420", "thursday": false, "tuesday": false, "wednesday": true}, "term": "202420"}], "reservedSeatSummary": null, "sectionAttributes": [], "instructionalMethod": "IP", "instructionalMethodDescription": "In Person"}, {"id": 142493, "term": "202420", "termDesc": "Fall 2024", "courseReferenceNumber": "21620", "partOfTerm": "1", "courseNumber": "246", "subject": "GEOL", "subjectDescription": "Geology", "sequenceNumber": "BBB", "campusDescription": "Main Campus", "scheduleTypeDescription": "Laboratory", "courseTitle": "Physical Geology", "creditHours": 0, "maximumEnrollment": 16, "enrollment": 0, "seatsAvailable": 16, "waitCapacity": 0, "waitCount": 0, "waitAvailable": 0, "crossList": null, "crossListCapacity": null, "crossListCount": null, "crossListAvailable": null, "creditHourHigh": 3, "creditHourLow": 0, "creditHourIndicator": "OR", "openSection": true, "linkIdentifier": "K2", "isSectionLinked": true, "subjectCourse": "GEOL246", "faculty": [], "meetingsFaculty": [{"category": "01", "class": "net.hedtech.banner.student.schedule.SectionSessionDecorator", "courseReferenceNumber": "21620", "faculty": [], "meetingTime": {"beginTime": "0900", "building": "KA", "buildingDescription": "Johnson-Cobbe Energy Centre", "campus": "MC", "campusDescription": "Main Campus", "category": "01", "class": "net.hedtech.banner.general.overall.MeetingTimeDecorator", "courseReferenceNumber": "21620", "creditHourSession": 0.0, "endDate": "12/16/2024", "endTime": "1050", "friday": false, "hoursWeek": 2.0, "meetingScheduleType": "B", "meetingType": "CLAS", "meetingTypeDescription": "Class", "monday": false, "room": "KA328", "saturday": false, "startDate": "09/03/2024", "sunday": false, "term": "202420", "thursday": false, "tuesday": false, "wednesday": true}, "term": "202420"}], "reservedSeatSummary": null, "sectionAttributes": [], "instructionalMethod": "IP", "instructionalMethodDescription": "In Person"}, {"id": 140447, "term": "202420", "termDesc": "Fall 2024", "courseReferenceNumber": "21621", "partOfTerm": "1", "courseNumber": "410", "subject": "GEOL", "subjectDescription": "Geology", "sequenceNumber": "A", "campusDescription": "Main Campus", "scheduleTypeDescription": "Lecture", "courseTitle": "Petroleum Geology", "creditHours": 1.5, "maximumEnrollment": 36, "enrollment": 0, "seatsAvailable": 36, "waitCapacity": 0, "waitCount": 0, "waitAvailable": 0, "crossList": null, "crossListCapacity": null, "crossListCount": null, "crossListAvailable": null, "creditHourHigh": null, "creditHourLow": 1.5, "creditHourIndicator": null, "openSection": true, "linkIdentifier": null, "isSectionLinked": false, "subjectCourse": "GEOL410", "faculty": [], "meetingsFaculty": [{"category": "01", "class": "net.hedtech.banner.student.schedule.SectionSessionDecorator", "courseReferenceNumber": "21621", "faculty": [], "meetingTime": {"beginTime": "1400", "building": "KA", "buildingDescription": "Johnson-Cobbe Energy Centre", "campus": "MC", "campusDescription": "Main Campus", "category": "01", "class": "net.hedtech.banner.general.overall.MeetingTimeDecorator", "courseReferenceNumber": "21621", "creditHourSession": 0.0, "endDate": "12/16/2024", "endTime": "1450", "friday": false, "hoursWeek": 1.0, "meetingScheduleType": "L", "meetingType": "CLAS", "meetingTypeDescription": "Class", "monday": false, "room": "KA338", "saturday": false, "startDate": "09/03/2024", "sunday": false, "term": "202420", "thursday": true, "tuesday": false, "wednesday": false}, "term": "202420"}, {"category": "01", "class": "net.hedtech.banner.student.schedule.SectionSessionDecorator", "courseReferenceNumber": "21621", "faculty": [], "meetingTime": {"beginTime": "1600", "building": "KA", "buildingDescription": "Johnson-Cobbe Energy Centre", "campus": "MC", "campusDescription": "Main Campus", "category": "01", "class": "net.hedtech.banner.general.overall.MeetingTimeDecorator", "courseReferenceNumber": "21621", "creditHourSession": 1.5, "endDate": "12/16/2024", "endTime": "1750", "friday": false, "hoursWeek": 2.0, "meetingScheduleType": "L", "meetingType": "CLAS", "meetingTypeDescription": "Class", "monday": false, "room": "KA337", "saturday": false, "startDate": "09/03/2024", "sunday": false, "term": "202420", "thursday": false, "tuesday": true, "wednesday": false}, "term": "202420"}], "reservedSeatSummary": null, "sectionAttributes": [], "instructionalMethod": "IP", "instructionalMethodDescription": "In Person"}, {"id": 142465, "term": "202420", "termDesc": "Fall 2024", "courseReferenceNumber": "21622", "partOfTerm": "1", "courseNumber": "410", "subject": "GEOL", "subjectDescription": "Geology", "sequenceNumber": "B", "campusDescription": "Main Campus", "scheduleTypeDescription": "Lecture", "courseTitle": "Petroleum Geology", "creditHours": 1.5, "maximumEnrollment": 36, "enrollment": 0, "seatsAvailable": 36, "waitCapacity": 0, "waitCount": 0, "waitAvailable": 0, "crossList": null, "crossListCapacity": null, "crossListCount": null, "crossListAvailable": null, "creditHourHigh": null, "creditHourLow": 1.5, "creditHourIndicator": null, "openSection": true, "linkIdentifier": null, "isSectionLinked": false, "subjectCourse": "GEOL410", "faculty": [], "meetingsFaculty": [{"category": "01", "class": "net.hedtech.banner.student.schedule.SectionSessionDecorator", "courseReferenceNumber": "21622", "faculty": [], "meetingTime": {"beginTime": "1100", "building": "KA", "buildingDescription": "Johnson-Cobbe Energy Centre", "campus": "MC", "campusDescription": "Main Campus", "category": "01", "class": "net.hedtech.banner.general.overall.MeetingTimeDecorator", "courseReferenceNumber": "21622", "creditHourSession": 1.5, "endDate": "12/16/2024", "endTime": "1250", "friday": false, "hoursWeek": 2.0, "meetingScheduleType": "L", "meetingType": "CLAS", "meetingTypeDescription": "Class", "monday": false, "room": "KA335", "saturday": false, "startDate": "09/03/2024", "sunday": false, "term": "202420", "thursday": false, "tuesday": false, "wednesday": true}, "term": "202420"}, {"category": "01", "class": "net.hedtech.banner.student.schedule.SectionSessionDecorator", "courseReferenceNumber": "21622", "faculty": [], "meetingTime": {"beginTime": "1300", "building": "KA", "buildingDescription": "Johnson-Cobbe Energy Centre", "campus": "MC", "campusDescription": "Main Campus", "category": "01", "class": "net.hedtech.banner.general.overall.MeetingTimeDecorator", "courseReferenceNumber": "21622", "creditHourSession": 0.0, "endDate": "12/16/2024", "endTime": "1350", "friday": false, "hoursWeek": 1.0, "meetingScheduleType": "L", "meetingType": "CLAS", "meetingTypeDescription": "Class", "monday": true, "room": "KA337", "saturday": false, "startDate": "09/03/2024", "sunday": false, "term": "202420", "thursday": false, "tuesday": false, "wednesday": false}, "term": "202420"}], "reservedSeatSummary": null, "sectionAttributes": [], "instructionalMethod": "IP", "instructionalMethodDescription": "In Person"}, {"id": 141901, "term": "202420", "termDesc": "Fall 2024", "courseReferenceNumber": "20066", "partOfTerm": null, "courseNumber": "410", "subject": "GEOL", "subjectDescription": "Geology", "sequenceNumber": "O2A", "campusDescription": "Online", "scheduleTypeDescription": "Internet Paced", "courseTitle": "Petroleum Geology", "creditHours": 1.5, "maximumEnrollment": 5, "enrollment": 0, "seatsAvailable": 5, "waitCapacity": 0, "waitCount": 0, "waitAvailable": 0, "crossList": null, "crossListCapacity": null, "crossListCount": null, "crossListAvailable": null, "creditHourHigh": null, "creditHourLow": 1.5, "creditHourIndicator": null, "openSection": true, "linkIdentifier": null, "isSectionLinked": false, "subjectCourse": "GEOL410", "faculty": [], "meetingsFaculty": [{"category": "01", "class": "net.hedtech.banner.student.schedule.SectionSessionDecorator", "courseReferenceNumber": "20066", "faculty": [], "meetingTime": {"beginTime": null, "building": "ONLINE", "buildingDescription": "Online", "campus": "OL", "campusDescription": "Online", "category": "01", "class": "net.hedtech.banner.general.overall.MeetingTimeDecorator", "courseReferenceNumber": "20066", "creditHourSession": 1.5, "endDate": "01/06/2025", "endTime": null, "friday": false, "hoursWeek": 0.0, "meetingScheduleType": "NP", "meetingType": "OA", "meetingTypeDescription": "Online Asynchronous", "monday": false, "room": "ONLINE27", "saturday": false, "startDate": "09/03/2024", "sunday": false, "term": "202420", "thursday": false, "tuesday": false, "wednesday": false}, "term": "202420"}], "reservedSeatSummary": null, "sectionAttributes": [], "instructionalMethod": "OL", "instructionalMethodDescription": "Online"}]}