{"code": "PRAC", "description": "Practicum", "entries": 14, "data": [{"id": 140879, "term": "202420", "termDesc": "Fall 2024", "courseReferenceNumber": "23202", "partOfTerm": "OS1", "courseNumber": "213", "subject": "PRAC", "subjectDescription": "Practicum", "sequenceNumber": "PHS", "campusDescription": "Off Site", "scheduleTypeDescription": "Clinical Practicum", "courseTitle": "Practicum", "creditHours": 3, "maximumEnrollment": 16, "enrollment": 0, "seatsAvailable": 16, "waitCapacity": 0, "waitCount": 0, "waitAvailable": 0, "crossList": null, "crossListCapacity": null, "crossListCount": null, "crossListAvailable": null, "creditHourHigh": null, "creditHourLow": 3, "creditHourIndicator": null, "openSection": true, "linkIdentifier": null, "isSectionLinked": false, "subjectCourse": "PRAC213", "faculty": [], "meetingsFaculty": [{"category": "03", "class": "net.hedtech.banner.student.schedule.SectionSessionDecorator", "courseReferenceNumber": "23202", "faculty": [], "meetingTime": {"beginTime": "1100", "building": "ONLINE", "buildingDescription": "Online", "campus": "OL", "campusDescription": "Online", "category": "03", "class": "net.hedtech.banner.general.overall.MeetingTimeDecorator", "courseReferenceNumber": "23202", "creditHourSession": 0.0, "endDate": "09/18/2024", "endTime": "1150", "friday": false, "hoursWeek": 1.0, "meetingScheduleType": "H", "meetingType": "OS", "meetingTypeDescription": "Online Synchronous", "monday": false, "room": "ONLINE44", "saturday": false, "startDate": "09/18/2024", "sunday": false, "term": "202420", "thursday": false, "tuesday": false, "wednesday": true}, "term": "202420"}, {"category": "02", "class": "net.hedtech.banner.student.schedule.SectionSessionDecorator", "courseReferenceNumber": "23202", "faculty": [], "meetingTime": {"beginTime": "1500", "building": "N", "buildingDescription": "Senator Burns Building", "campus": "MC", "campusDescription": "Main Campus", "category": "02", "class": "net.hedtech.banner.general.overall.MeetingTimeDecorator", "courseReferenceNumber": "23202", "creditHourSession": 0.0, "endDate": "09/13/2024", "endTime": "1550", "friday": false, "hoursWeek": 1.0, "meetingScheduleType": "H", "meetingType": "CLAS", "meetingTypeDescription": "Class", "monday": false, "room": "NK101", "saturday": false, "startDate": "09/03/2024", "sunday": false, "term": "202420", "thursday": false, "tuesday": false, "wednesday": true}, "term": "202420"}, {"category": "01", "class": "net.hedtech.banner.student.schedule.SectionSessionDecorator", "courseReferenceNumber": "23202", "faculty": [], "meetingTime": {"beginTime": null, "building": "OFFCMP", "buildingDescription": "Off Site", "campus": "OC", "campusDescription": "Off Site", "category": "01", "class": "net.hedtech.banner.general.overall.MeetingTimeDecorator", "courseReferenceNumber": "23202", "creditHourSession": 3.0, "endDate": "10/25/2024", "endTime": null, "friday": false, "hoursWeek": 0.0, "meetingScheduleType": "H", "meetingType": "PRAC", "meetingTypeDescription": "Practicum", "monday": false, "room": "OFFCMP", "saturday": false, "startDate": "09/23/2024", "sunday": false, "term": "202420", "thursday": false, "tuesday": false, "wednesday": false}, "term": "202420"}], "reservedSeatSummary": null, "sectionAttributes": [], "instructionalMethod": "BL", "instructionalMethodDescription": "Blended - In Person and Online"}, {"id": 141608, "term": "202420", "termDesc": "Fall 2024", "courseReferenceNumber": "20129", "partOfTerm": null, "courseNumber": "249", "subject": "PRAC", "subjectDescription": "Practicum", "sequenceNumber": "O2A", "campusDescription": "Online", "scheduleTypeDescription": "Practicum", "courseTitle": "Career Advancement Practicum", "creditHours": 3, "maximumEnrollment": 100, "enrollment": 0, "seatsAvailable": 100, "waitCapacity": 0, "waitCount": 0, "waitAvailable": 0, "crossList": null, "crossListCapacity": null, "crossListCount": null, "crossListAvailable": null, "creditHourHigh": null, "creditHourLow": 3, "creditHourIndicator": null, "openSection": true, "linkIdentifier": null, "isSectionLinked": false, "subjectCourse": "PRAC249", "faculty": [], "meetingsFaculty": [{"category": "01", "class": "net.hedtech.banner.student.schedule.SectionSessionDecorator", "courseReferenceNumber": "20129", "faculty": [], "meetingTime": {"beginTime": null, "building": "OFFCMP", "buildingDescription": "Off Site", "campus": "OC", "campusDescription": "Off Site", "category": "01", "class": "net.hedtech.banner.general.overall.MeetingTimeDecorator", "courseReferenceNumber": "20129", "creditHourSession": 3.0, "endDate": "12/13/2024", "endTime": null, "friday": false, "hoursWeek": 0.0, "meetingScheduleType": "P", "meetingType": "PRAC", "meetingTypeDescription": "Practicum", "monday": false, "room": "OFFCMP", "saturday": false, "startDate": "09/03/2024", "sunday": false, "term": "202420", "thursday": false, "tuesday": false, "wednesday": false}, "term": "202420"}], "reservedSeatSummary": null, "sectionAttributes": [], "instructionalMethod": "OL", "instructionalMethodDescription": "Online"}, {"id": 143451, "term": "202420", "termDesc": "Fall 2024", "courseReferenceNumber": "23509", "partOfTerm": "X", "courseNumber": "252", "subject": "PRAC", "subjectDescription": "Practicum", "sequenceNumber": "PCW", "campusDescription": "Off Site", "scheduleTypeDescription": "Clinical Practicum", "courseTitle": "Ambulance Practicum", "creditHours": 3, "maximumEnrollment": 18, "enrollment": 0, "seatsAvailable": 18, "waitCapacity": 0, "waitCount": 0, "waitAvailable": 0, "crossList": null, "crossListCapacity": null, "crossListCount": null, "crossListAvailable": null, "creditHourHigh": null, "creditHourLow": 3, "creditHourIndicator": null, "openSection": true, "linkIdentifier": null, "isSectionLinked": false, "subjectCourse": "PRAC252", "faculty": [], "meetingsFaculty": [{"category": "01", "class": "net.hedtech.banner.student.schedule.SectionSessionDecorator", "courseReferenceNumber": "23509", "faculty": [], "meetingTime": {"beginTime": null, "building": "OFFCMP", "buildingDescription": "Off Site", "campus": "OC", "campusDescription": "Off Site", "category": "01", "class": "net.hedtech.banner.general.overall.MeetingTimeDecorator", "courseReferenceNumber": "23509", "creditHourSession": 3.0, "endDate": "12/16/2024", "endTime": null, "friday": false, "hoursWeek": 0.0, "meetingScheduleType": "H", "meetingType": "OA", "meetingTypeDescription": "Online Asynchronous", "monday": false, "room": "OFFCMP", "saturday": false, "startDate": "09/03/2024", "sunday": false, "term": "202420", "thursday": false, "tuesday": false, "wednesday": false}, "term": "202420"}], "reservedSeatSummary": null, "sectionAttributes": [], "instructionalMethod": "OT", "instructionalMethodDescription": "Other"}, {"id": 141055, "term": "202420", "termDesc": "Fall 2024", "courseReferenceNumber": "22550", "partOfTerm": "1", "courseNumber": "271", "subject": "PRAC", "subjectDescription": "Practicum", "sequenceNumber": "MLA", "campusDescription": "Off Site", "scheduleTypeDescription": "Clinical Practicum", "courseTitle": "Clinical Placement", "creditHours": 3, "maximumEnrollment": 11, "enrollment": 0, "seatsAvailable": 11, "waitCapacity": 0, "waitCount": 0, "waitAvailable": 0, "crossList": null, "crossListCapacity": null, "crossListCount": null, "crossListAvailable": null, "creditHourHigh": null, "creditHourLow": 3, "creditHourIndicator": null, "openSection": true, "linkIdentifier": null, "isSectionLinked": false, "subjectCourse": "PRAC271", "faculty": [], "meetingsFaculty": [{"category": "01", "class": "net.hedtech.banner.student.schedule.SectionSessionDecorator", "courseReferenceNumber": "22550", "faculty": [], "meetingTime": {"beginTime": null, "building": "OFFCMP", "buildingDescription": "Off Site", "campus": "OC", "campusDescription": "Off Site", "category": "01", "class": "net.hedtech.banner.general.overall.MeetingTimeDecorator", "courseReferenceNumber": "22550", "creditHourSession": 3.0, "endDate": "10/29/2024", "endTime": null, "friday": false, "hoursWeek": 0.0, "meetingScheduleType": "H", "meetingType": "OA", "meetingTypeDescription": "Online Asynchronous", "monday": false, "room": "OFFCMP", "saturday": false, "startDate": "09/03/2024", "sunday": false, "term": "202420", "thursday": false, "tuesday": false, "wednesday": false}, "term": "202420"}], "reservedSeatSummary": null, "sectionAttributes": [], "instructionalMethod": "OT", "instructionalMethodDescription": "Other"}, {"id": 140878, "term": "202420", "termDesc": "Fall 2024", "courseReferenceNumber": "22551", "partOfTerm": "1", "courseNumber": "279", "subject": "PRAC", "subjectDescription": "Practicum", "sequenceNumber": "EVE", "campusDescription": "Off Site", "scheduleTypeDescription": "Clinical Practicum", "courseTitle": "Practicum", "creditHours": 1.5, "maximumEnrollment": 30, "enrollment": 0, "seatsAvailable": 30, "waitCapacity": 0, "waitCount": 0, "waitAvailable": 0, "crossList": null, "crossListCapacity": null, "crossListCount": null, "crossListAvailable": null, "creditHourHigh": null, "creditHourLow": 1.5, "creditHourIndicator": null, "openSection": true, "linkIdentifier": null, "isSectionLinked": false, "subjectCourse": "PRAC279", "faculty": [], "meetingsFaculty": [{"category": "01", "class": "net.hedtech.banner.student.schedule.SectionSessionDecorator", "courseReferenceNumber": "22551", "faculty": [], "meetingTime": {"beginTime": null, "building": "OFFCMP", "buildingDescription": "Off Site", "campus": "OC", "campusDescription": "Off Site", "category": "01", "class": "net.hedtech.banner.general.overall.MeetingTimeDecorator", "courseReferenceNumber": "22551", "creditHourSession": 1.5, "endDate": "10/11/2024", "endTime": null, "friday": false, "hoursWeek": 0.0, "meetingScheduleType": "H", "meetingType": "PRAC", "meetingTypeDescription": "Practicum", "monday": false, "room": "OFFCMP", "saturday": false, "startDate": "09/03/2024", "sunday": false, "term": "202420", "thursday": false, "tuesday": false, "wednesday": false}, "term": "202420"}], "reservedSeatSummary": null, "sectionAttributes": [], "instructionalMethod": "OT", "instructionalMethodDescription": "Other"}, {"id": 140595, "term": "202420", "termDesc": "Fall 2024", "courseReferenceNumber": "20130", "partOfTerm": null, "courseNumber": "297", "subject": "PRAC", "subjectDescription": "Practicum", "sequenceNumber": "FD1", "campusDescription": "Off Site", "scheduleTypeDescription": "Clinical Practicum", "courseTitle": "Practicum", "creditHours": 6, "maximumEnrollment": 18, "enrollment": 0, "seatsAvailable": 18, "waitCapacity": 0, "waitCount": 0, "waitAvailable": 0, "crossList": null, "crossListCapacity": null, "crossListCount": null, "crossListAvailable": null, "creditHourHigh": 6, "creditHourLow": 0, "creditHourIndicator": "OR", "openSection": true, "linkIdentifier": null, "isSectionLinked": false, "subjectCourse": "PRAC297", "faculty": [], "meetingsFaculty": [{"category": "02", "class": "net.hedtech.banner.student.schedule.SectionSessionDecorator", "courseReferenceNumber": "20130", "faculty": [], "meetingTime": {"beginTime": "0800", "building": null, "buildingDescription": null, "campus": null, "campusDescription": null, "category": "02", "class": "net.hedtech.banner.general.overall.MeetingTimeDecorator", "courseReferenceNumber": "20130", "creditHourSession": 0.0, "endDate": "02/21/2025", "endTime": "1150", "friday": true, "hoursWeek": 4.0, "meetingScheduleType": "H", "meetingType": "CLAS", "meetingTypeDescription": "Class", "monday": false, "room": null, "saturday": false, "startDate": "02/21/2025", "sunday": false, "term": "202420", "thursday": false, "tuesday": false, "wednesday": false}, "term": "202420"}, {"category": "01", "class": "net.hedtech.banner.student.schedule.SectionSessionDecorator", "courseReferenceNumber": "20130", "faculty": [], "meetingTime": {"beginTime": null, "building": "OFFCMP", "buildingDescription": "Off Site", "campus": "OC", "campusDescription": "Off Site", "category": "01", "class": "net.hedtech.banner.general.overall.MeetingTimeDecorator", "courseReferenceNumber": "20130", "creditHourSession": 6.0, "endDate": "02/21/2025", "endTime": null, "friday": false, "hoursWeek": 0.0, "meetingScheduleType": "H", "meetingType": "PRAC", "meetingTypeDescription": "Practicum", "monday": false, "room": "OFFCMP", "saturday": false, "startDate": "09/03/2024", "sunday": false, "term": "202420", "thursday": false, "tuesday": false, "wednesday": false}, "term": "202420"}], "reservedSeatSummary": null, "sectionAttributes": [], "instructionalMethod": "OT", "instructionalMethodDescription": "Other"}, {"id": 140914, "term": "202420", "termDesc": "Fall 2024", "courseReferenceNumber": "22552", "partOfTerm": "1", "courseNumber": "297", "subject": "PRAC", "subjectDescription": "Practicum", "sequenceNumber": "MDR", "campusDescription": "Main Campus", "scheduleTypeDescription": "Clinical Practicum", "courseTitle": "Practicum", "creditHours": 6, "maximumEnrollment": 34, "enrollment": 0, "seatsAvailable": 34, "waitCapacity": 0, "waitCount": 0, "waitAvailable": 0, "crossList": null, "crossListCapacity": null, "crossListCount": null, "crossListAvailable": null, "creditHourHigh": 6, "creditHourLow": 0, "creditHourIndicator": "OR", "openSection": true, "linkIdentifier": null, "isSectionLinked": false, "subjectCourse": "PRAC297", "faculty": [], "meetingsFaculty": [{"category": "02", "class": "net.hedtech.banner.student.schedule.SectionSessionDecorator", "courseReferenceNumber": "22552", "faculty": [], "meetingTime": {"beginTime": "0800", "building": null, "buildingDescription": null, "campus": null, "campusDescription": null, "category": "02", "class": "net.hedtech.banner.general.overall.MeetingTimeDecorator", "courseReferenceNumber": "22552", "creditHourSession": 0.0, "endDate": "02/21/2025", "endTime": "1150", "friday": true, "hoursWeek": 4.0, "meetingScheduleType": "H", "meetingType": "CLAS", "meetingTypeDescription": "Class", "monday": false, "room": null, "saturday": false, "startDate": "02/21/2025", "sunday": false, "term": "202420", "thursday": false, "tuesday": false, "wednesday": false}, "term": "202420"}, {"category": "02", "class": "net.hedtech.banner.student.schedule.SectionSessionDecorator", "courseReferenceNumber": "22552", "faculty": [], "meetingTime": {"beginTime": "1300", "building": null, "buildingDescription": null, "campus": null, "campusDescription": null, "category": "02", "class": "net.hedtech.banner.general.overall.MeetingTimeDecorator", "courseReferenceNumber": "22552", "creditHourSession": 0.0, "endDate": "02/21/2025", "endTime": "1650", "friday": true, "hoursWeek": 4.0, "meetingScheduleType": "H", "meetingType": "CLAS", "meetingTypeDescription": "Class", "monday": false, "room": null, "saturday": false, "startDate": "02/21/2025", "sunday": false, "term": "202420", "thursday": false, "tuesday": false, "wednesday": false}, "term": "202420"}, {"category": "01", "class": "net.hedtech.banner.student.schedule.SectionSessionDecorator", "courseReferenceNumber": "22552", "faculty": [], "meetingTime": {"beginTime": null, "building": "OFFCMP", "buildingDescription": "Off Site", "campus": "OC", "campusDescription": "Off Site", "category": "01", "class": "net.hedtech.banner.general.overall.MeetingTimeDecorator", "courseReferenceNumber": "22552", "creditHourSession": 6.0, "endDate": "02/21/2025", "endTime": null, "friday": false, "hoursWeek": 0.0, "meetingScheduleType": "H", "meetingType": "PRAC", "meetingTypeDescription": "Practicum", "monday": false, "room": "OFFCMP", "saturday": false, "startDate": "09/03/2024", "sunday": false, "term": "202420", "thursday": false, "tuesday": false, "wednesday": false}, "term": "202420"}], "reservedSeatSummary": null, "sectionAttributes": [], "instructionalMethod": "OT", "instructionalMethodDescription": "Other"}, {"id": 139690, "term": "202420", "termDesc": "Fall 2024", "courseReferenceNumber": "22553", "partOfTerm": "1", "courseNumber": "309", "subject": "PRAC", "subjectDescription": "Practicum", "sequenceNumber": "A", "campusDescription": "Off Site", "scheduleTypeDescription": "Clinical Practicum", "courseTitle": "Practicum 1", "creditHours": 6, "maximumEnrollment": 28, "enrollment": 0, "seatsAvailable": 28, "waitCapacity": 0, "waitCount": 0, "waitAvailable": 0, "crossList": null, "crossListCapacity": null, "crossListCount": null, "crossListAvailable": null, "creditHourHigh": null, "creditHourLow": 6, "creditHourIndicator": null, "openSection": true, "linkIdentifier": null, "isSectionLinked": false, "subjectCourse": "PRAC309", "faculty": [], "meetingsFaculty": [{"category": "01", "class": "net.hedtech.banner.student.schedule.SectionSessionDecorator", "courseReferenceNumber": "22553", "faculty": [], "meetingTime": {"beginTime": null, "building": "OFFCMP", "buildingDescription": "Off Site", "campus": "OC", "campusDescription": "Off Site", "category": "01", "class": "net.hedtech.banner.general.overall.MeetingTimeDecorator", "courseReferenceNumber": "22553", "creditHourSession": 6.0, "endDate": "12/16/2024", "endTime": null, "friday": false, "hoursWeek": 0.0, "meetingScheduleType": "H", "meetingType": "PRAC", "meetingTypeDescription": "Practicum", "monday": false, "room": "OFFCMP", "saturday": false, "startDate": "09/03/2024", "sunday": false, "term": "202420", "thursday": false, "tuesday": false, "wednesday": false}, "term": "202420"}], "reservedSeatSummary": null, "sectionAttributes": [], "instructionalMethod": "BL", "instructionalMethodDescription": "Blended - In Person and Online"}, {"id": 139414, "term": "202420", "termDesc": "Fall 2024", "courseReferenceNumber": "22554", "partOfTerm": "1", "courseNumber": "320", "subject": "PRAC", "subjectDescription": "Practicum", "sequenceNumber": "A", "campusDescription": "Main Campus", "scheduleTypeDescription": "Lecture", "courseTitle": "Practicum Preparation", "creditHours": 1.5, "maximumEnrollment": 32, "enrollment": 0, "seatsAvailable": 32, "waitCapacity": 0, "waitCount": 0, "waitAvailable": 0, "crossList": null, "crossListCapacity": null, "crossListCount": null, "crossListAvailable": null, "creditHourHigh": null, "creditHourLow": 1.5, "creditHourIndicator": null, "openSection": true, "linkIdentifier": null, "isSectionLinked": false, "subjectCourse": "PRAC320", "faculty": [], "meetingsFaculty": [{"category": "01", "class": "net.hedtech.banner.student.schedule.SectionSessionDecorator", "courseReferenceNumber": "22554", "faculty": [], "meetingTime": {"beginTime": "1200", "building": "N", "buildingDescription": "Senator Burns Building", "campus": "MC", "campusDescription": "Main Campus", "category": "01", "class": "net.hedtech.banner.general.overall.MeetingTimeDecorator", "courseReferenceNumber": "22554", "creditHourSession": 1.5, "endDate": "12/16/2024", "endTime": "1250", "friday": false, "hoursWeek": 1.0, "meetingScheduleType": "L", "meetingType": "CLAS", "meetingTypeDescription": "Class", "monday": true, "room": "NL302", "saturday": false, "startDate": "09/03/2024", "sunday": false, "term": "202420", "thursday": false, "tuesday": false, "wednesday": false}, "term": "202420"}], "reservedSeatSummary": null, "sectionAttributes": [], "instructionalMethod": "IP", "instructionalMethodDescription": "In Person"}, {"id": 143225, "term": "202420", "termDesc": "Fall 2024", "courseReferenceNumber": "22555", "partOfTerm": "1", "courseNumber": "320", "subject": "PRAC", "subjectDescription": "Practicum", "sequenceNumber": "O2A", "campusDescription": "Off Site", "scheduleTypeDescription": "Lecture", "courseTitle": "Practicum Preparation", "creditHours": 1.5, "maximumEnrollment": 8, "enrollment": 0, "seatsAvailable": 8, "waitCapacity": 0, "waitCount": 0, "waitAvailable": 0, "crossList": null, "crossListCapacity": null, "crossListCount": null, "crossListAvailable": null, "creditHourHigh": null, "creditHourLow": 1.5, "creditHourIndicator": null, "openSection": true, "linkIdentifier": null, "isSectionLinked": false, "subjectCourse": "PRAC320", "faculty": [], "meetingsFaculty": [{"category": "01", "class": "net.hedtech.banner.student.schedule.SectionSessionDecorator", "courseReferenceNumber": "22555", "faculty": [], "meetingTime": {"beginTime": null, "building": "OFFCMP", "buildingDescription": "Off Site", "campus": "OC", "campusDescription": "Off Site", "category": "01", "class": "net.hedtech.banner.general.overall.MeetingTimeDecorator", "courseReferenceNumber": "22555", "creditHourSession": 1.5, "endDate": "12/14/2024", "endTime": null, "friday": false, "hoursWeek": 0.0, "meetingScheduleType": "L", "meetingType": "OA", "meetingTypeDescription": "Online Asynchronous", "monday": false, "room": "OFFCMP", "saturday": false, "startDate": "09/03/2024", "sunday": false, "term": "202420", "thursday": false, "tuesday": false, "wednesday": false}, "term": "202420"}], "reservedSeatSummary": null, "sectionAttributes": [], "instructionalMethod": "OL", "instructionalMethodDescription": "Online"}, {"id": 141617, "term": "202420", "termDesc": "Fall 2024", "courseReferenceNumber": "20131", "partOfTerm": null, "courseNumber": "392", "subject": "PRAC", "subjectDescription": "Practicum", "sequenceNumber": "O2A", "campusDescription": "Off Site", "scheduleTypeDescription": "Practicum", "courseTitle": "Library Practicum", "creditHours": 3, "maximumEnrollment": 8, "enrollment": 0, "seatsAvailable": 8, "waitCapacity": 0, "waitCount": 0, "waitAvailable": 0, "crossList": null, "crossListCapacity": null, "crossListCount": null, "crossListAvailable": null, "creditHourHigh": null, "creditHourLow": 3, "creditHourIndicator": null, "openSection": true, "linkIdentifier": null, "isSectionLinked": false, "subjectCourse": "PRAC392", "faculty": [], "meetingsFaculty": [{"category": "01", "class": "net.hedtech.banner.student.schedule.SectionSessionDecorator", "courseReferenceNumber": "20131", "faculty": [], "meetingTime": {"beginTime": null, "building": "OFFCMP", "buildingDescription": "Off Site", "campus": "OC", "campusDescription": "Off Site", "category": "01", "class": "net.hedtech.banner.general.overall.MeetingTimeDecorator", "courseReferenceNumber": "20131", "creditHourSession": 3.0, "endDate": "12/14/2024", "endTime": null, "friday": false, "hoursWeek": 0.0, "meetingScheduleType": "P", "meetingType": "OA", "meetingTypeDescription": "Online Asynchronous", "monday": false, "room": "OFFCMP", "saturday": false, "startDate": "09/03/2024", "sunday": false, "term": "202420", "thursday": false, "tuesday": false, "wednesday": false}, "term": "202420"}], "reservedSeatSummary": null, "sectionAttributes": [], "instructionalMethod": "OT", "instructionalMethodDescription": "Other"}, {"id": 142929, "term": "202420", "termDesc": "Fall 2024", "courseReferenceNumber": "22556", "partOfTerm": "1", "courseNumber": "395", "subject": "PRAC", "subjectDescription": "Practicum", "sequenceNumber": "A", "campusDescription": "Off Site", "scheduleTypeDescription": "Practicum", "courseTitle": "New Media Practicum", "creditHours": 1.5, "maximumEnrollment": 40, "enrollment": 0, "seatsAvailable": 40, "waitCapacity": 0, "waitCount": 0, "waitAvailable": 0, "crossList": null, "crossListCapacity": null, "crossListCount": null, "crossListAvailable": null, "creditHourHigh": null, "creditHourLow": 1.5, "creditHourIndicator": null, "openSection": true, "linkIdentifier": null, "isSectionLinked": false, "subjectCourse": "PRAC395", "faculty": [], "meetingsFaculty": [{"category": "01", "class": "net.hedtech.banner.student.schedule.SectionSessionDecorator", "courseReferenceNumber": "22556", "faculty": [], "meetingTime": {"beginTime": "0800", "building": "ONLINE", "buildingDescription": "Online", "campus": "OL", "campusDescription": "Online", "category": "01", "class": "net.hedtech.banner.general.overall.MeetingTimeDecorator", "courseReferenceNumber": "22556", "creditHourSession": 0.0, "endDate": "12/16/2024", "endTime": "1050", "friday": false, "hoursWeek": 3.0, "meetingScheduleType": "P", "meetingType": "OS", "meetingTypeDescription": "Online Synchronous", "monday": false, "room": "ONLINE83", "saturday": false, "startDate": "09/03/2024", "sunday": false, "term": "202420", "thursday": false, "tuesday": true, "wednesday": false}, "term": "202420"}, {"category": "01", "class": "net.hedtech.banner.student.schedule.SectionSessionDecorator", "courseReferenceNumber": "22556", "faculty": [], "meetingTime": {"beginTime": "0800", "building": "ONLINE", "buildingDescription": "Online", "campus": "OL", "campusDescription": "Online", "category": "01", "class": "net.hedtech.banner.general.overall.MeetingTimeDecorator", "courseReferenceNumber": "22556", "creditHourSession": 1.5, "endDate": "12/16/2024", "endTime": "1050", "friday": false, "hoursWeek": 3.0, "meetingScheduleType": "P", "meetingType": "OS", "meetingTypeDescription": "Online Synchronous", "monday": false, "room": "ONLINE83", "saturday": false, "startDate": "09/03/2024", "sunday": false, "term": "202420", "thursday": true, "tuesday": false, "wednesday": false}, "term": "202420"}], "reservedSeatSummary": null, "sectionAttributes": [], "instructionalMethod": "OL", "instructionalMethodDescription": "Online"}, {"id": 141276, "term": "202420", "termDesc": "Fall 2024", "courseReferenceNumber": "20132", "partOfTerm": null, "courseNumber": "400", "subject": "PRAC", "subjectDescription": "Practicum", "sequenceNumber": "O2A", "campusDescription": "Off Site", "scheduleTypeDescription": "Practicum - Applied Degree", "courseTitle": "Practicum I for BAPT", "creditHours": 15, "maximumEnrollment": 50, "enrollment": 0, "seatsAvailable": 50, "waitCapacity": 0, "waitCount": 0, "waitAvailable": 0, "crossList": null, "crossListCapacity": null, "crossListCount": null, "crossListAvailable": null, "creditHourHigh": null, "creditHourLow": 15, "creditHourIndicator": null, "openSection": true, "linkIdentifier": null, "isSectionLinked": false, "subjectCourse": "PRAC400", "faculty": [], "meetingsFaculty": [{"category": "01", "class": "net.hedtech.banner.student.schedule.SectionSessionDecorator", "courseReferenceNumber": "20132", "faculty": [], "meetingTime": {"beginTime": null, "building": "OFFCMP", "buildingDescription": "Off Site", "campus": "OC", "campusDescription": "Off Site", "category": "01", "class": "net.hedtech.banner.general.overall.MeetingTimeDecorator", "courseReferenceNumber": "20132", "creditHourSession": 15.0, "endDate": "08/29/2025", "endTime": null, "friday": false, "hoursWeek": 0.0, "meetingScheduleType": "PA", "meetingType": "OA", "meetingTypeDescription": "Online Asynchronous", "monday": false, "room": "OFFCMP", "saturday": false, "startDate": "09/03/2024", "sunday": false, "term": "202420", "thursday": false, "tuesday": false, "wednesday": false}, "term": "202420"}], "reservedSeatSummary": null, "sectionAttributes": [], "instructionalMethod": "OL", "instructionalMethodDescription": "Online"}, {"id": 141273, "term": "202420", "termDesc": "Fall 2024", "courseReferenceNumber": "20133", "partOfTerm": null, "courseNumber": "410", "subject": "PRAC", "subjectDescription": "Practicum", "sequenceNumber": "O2A", "campusDescription": "Off Site", "scheduleTypeDescription": "Practicum - Applied Degree", "courseTitle": "Practicum Project for BAPT", "creditHours": 15, "maximumEnrollment": 50, "enrollment": 0, "seatsAvailable": 50, "waitCapacity": 0, "waitCount": 0, "waitAvailable": 0, "crossList": null, "crossListCapacity": null, "crossListCount": null, "crossListAvailable": null, "creditHourHigh": null, "creditHourLow": 15, "creditHourIndicator": null, "openSection": true, "linkIdentifier": null, "isSectionLinked": false, "subjectCourse": "PRAC410", "faculty": [], "meetingsFaculty": [{"category": "01", "class": "net.hedtech.banner.student.schedule.SectionSessionDecorator", "courseReferenceNumber": "20133", "faculty": [], "meetingTime": {"beginTime": null, "building": "OFFCMP", "buildingDescription": "Off Site", "campus": "OC", "campusDescription": "Off Site", "category": "01", "class": "net.hedtech.banner.general.overall.MeetingTimeDecorator", "courseReferenceNumber": "20133", "creditHourSession": 15.0, "endDate": "08/29/2025", "endTime": null, "friday": false, "hoursWeek": 0.0, "meetingScheduleType": "PA", "meetingType": "OA", "meetingTypeDescription": "Online Asynchronous", "monday": false, "room": "OFFCMP", "saturday": false, "startDate": "09/03/2024", "sunday": false, "term": "202420", "thursday": false, "tuesday": false, "wednesday": false}, "term": "202420"}], "reservedSeatSummary": null, "sectionAttributes": [], "instructionalMethod": "OL", "instructionalMethodDescription": "Online"}]}